{"name": "Spell Scrolls (5)", "img": "icons/svg/d20-grey.svg", "description": "", "results": [{"type": 2, "weight": 1, "range": [1, 1], "drawn": false, "text": "Scroll of Shadow Evocation", "img": "systems/pf1/icons/items/inventory/scroll-magic.jpg", "documentCollection": "world.pf1-scrolls", "documentId": "00FaZcuEHjPSLhkk", "flags": {}}, {"type": 2, "weight": 1, "range": [2, 2], "drawn": false, "text": "Scroll of Entrap Spirit", "img": "systems/pf1/icons/items/inventory/scroll-magic.jpg", "documentCollection": "world.pf1-scrolls", "documentId": "0DjtXu6SQMZ4jYYT", "flags": {}}, {"type": 2, "weight": 1, "range": [3, 3], "drawn": false, "text": "Scroll of Globe of Tranquil Water", "img": "systems/pf1/icons/items/inventory/scroll-magic.jpg", "documentCollection": "world.pf1-scrolls", "documentId": "0UQfPPDyUWZX3Knx", "flags": {}}, {"type": 2, "weight": 1, "range": [4, 4], "drawn": false, "text": "Scroll of Draconic Suppression", "img": "systems/pf1/icons/items/inventory/scroll-magic.jpg", "documentCollection": "world.pf1-scrolls", "documentId": "0WWX75St1svvRyRj", "flags": {}}, {"type": 2, "weight": 1, "range": [5, 5], "drawn": false, "text": "Scroll of Nex's Secret Workshop", "img": "systems/pf1/icons/items/inventory/scroll-magic.jpg", "documentCollection": "world.pf1-scrolls", "documentId": "0ik01mwJ1fRi9C1V", "flags": {}}, {"type": 2, "weight": 1, "range": [6, 6], "drawn": false, "text": "Scroll of Khain's Army", "img": "systems/pf1/icons/items/inventory/scroll-magic.jpg", "documentCollection": "world.pf1-scrolls", "documentId": "0kgOc2ka5OR9TWfs", "flags": {}}, {"type": 2, "weight": 1, "range": [7, 7], "drawn": false, "text": "Scroll of Symbol of Pain", "img": "systems/pf1/icons/items/inventory/scroll-magic.jpg", "documentCollection": "world.pf1-scrolls", "documentId": "120zIlRyOFTHpmTY", "flags": {}}, {"type": 2, "weight": 1, "range": [8, 8], "drawn": false, "text": "Scroll of Synapse Overload", "img": "systems/pf1/icons/items/inventory/scroll-magic.jpg", "documentCollection": "world.pf1-scrolls", "documentId": "1AFsbfBgYd2aKd2h", "flags": {}}, {"type": 2, "weight": 1, "range": [9, 9], "drawn": false, "text": "Scroll of Dispel Law", "img": "systems/pf1/icons/items/inventory/scroll-magic.jpg", "documentCollection": "world.pf1-scrolls", "documentId": "1MvKoVRKuehL4qwD", "flags": {}}, {"type": 2, "weight": 1, "range": [10, 10], "drawn": false, "text": "Scroll of Overland Flight", "img": "systems/pf1/icons/items/inventory/scroll-magic.jpg", "documentCollection": "world.pf1-scrolls", "documentId": "1fGDQ7eQPhySjCB3", "flags": {}}, {"type": 2, "weight": 1, "range": [11, 11], "drawn": false, "text": "Scroll of Raise Animal Companion", "img": "systems/pf1/icons/items/inventory/scroll-magic.jpg", "documentCollection": "world.pf1-scrolls", "documentId": "1h8kMp6sR3N2lPqQ", "flags": {}}, {"type": 2, "weight": 1, "range": [12, 12], "drawn": false, "text": "Scroll of Dismissal", "img": "systems/pf1/icons/items/inventory/scroll-magic.jpg", "documentCollection": "world.pf1-scrolls", "documentId": "2KqmHIBcNpVEfWqJ", "flags": {}}, {"type": 2, "weight": 1, "range": [13, 13], "drawn": false, "text": "Scroll of Cloudkill", "img": "systems/pf1/icons/items/inventory/scroll-magic.jpg", "documentCollection": "world.pf1-scrolls", "documentId": "2ZiOMwoQkxin6Grp", "flags": {}}, {"type": 2, "weight": 1, "range": [14, 14], "drawn": false, "text": "Scroll of Permanency", "img": "systems/pf1/icons/items/inventory/scroll-magic.jpg", "documentCollection": "world.pf1-scrolls", "documentId": "2cS6oKuBV6I4vRrb", "flags": {}}, {"type": 2, "weight": 1, "range": [15, 15], "drawn": false, "text": "Scroll of Vermin Shape II", "img": "systems/pf1/icons/items/inventory/scroll-magic.jpg", "documentCollection": "world.pf1-scrolls", "documentId": "2uxWPO9K2NoQ42jQ", "flags": {}}, {"type": 2, "weight": 1, "range": [16, 16], "drawn": false, "text": "Scroll of Peacebond, Greater", "img": "systems/pf1/icons/items/inventory/scroll-magic.jpg", "documentCollection": "world.pf1-scrolls", "documentId": "2wtSW5ciCTEMkAsp", "flags": {}}, {"type": 2, "weight": 1, "range": [17, 17], "drawn": false, "text": "Scroll of Thought Worm IV", "img": "systems/pf1/icons/items/inventory/scroll-magic.jpg", "documentCollection": "world.pf1-scrolls", "documentId": "2z7MXEEDINg0xtTA", "flags": {}}, {"type": 2, "weight": 1, "range": [18, 18], "drawn": false, "text": "Scroll of Unseen Crew", "img": "systems/pf1/icons/items/inventory/scroll-magic.jpg", "documentCollection": "world.pf1-scrolls", "documentId": "2zi1tv97cgZMSobE", "flags": {}}, {"type": 2, "weight": 1, "range": [19, 19], "drawn": false, "text": "Scroll of Touch of Slumber", "img": "systems/pf1/icons/items/inventory/scroll-magic.jpg", "documentCollection": "world.pf1-scrolls", "documentId": "3IPSyju6VgVeWiH1", "flags": {}}, {"type": 2, "weight": 1, "range": [20, 20], "drawn": false, "text": "Scroll of Dispel Evil", "img": "systems/pf1/icons/items/inventory/scroll-magic.jpg", "documentCollection": "world.pf1-scrolls", "documentId": "3L1fdwXszHcPGZpZ", "flags": {}}, {"type": 2, "weight": 1, "range": [21, 21], "drawn": false, "text": "Scroll of Truespeak", "img": "systems/pf1/icons/items/inventory/scroll-magic.jpg", "documentCollection": "world.pf1-scrolls", "documentId": "3saRJsiGigUx1Dgw", "flags": {}}, {"type": 2, "weight": 1, "range": [22, 22], "drawn": false, "text": "Scroll of Flesh Puppet Horde", "img": "systems/pf1/icons/items/inventory/scroll-magic.jpg", "documentCollection": "world.pf1-scrolls", "documentId": "3smdOfCTo7R6Xvjh", "flags": {}}, {"type": 2, "weight": 1, "range": [23, 23], "drawn": false, "text": "Scroll of Phantasmal Web", "img": "systems/pf1/icons/items/inventory/scroll-magic.jpg", "documentCollection": "world.pf1-scrolls", "documentId": "3y0nlvGUXLlHXiXg", "flags": {}}, {"type": 2, "weight": 1, "range": [24, 24], "drawn": false, "text": "Scroll of Hungry Earth", "img": "systems/pf1/icons/items/inventory/scroll-magic.jpg", "documentCollection": "world.pf1-scrolls", "documentId": "42e1tCDwpWtpS3mY", "flags": {}}, {"type": 2, "weight": 1, "range": [25, 25], "drawn": false, "text": "Scroll of Compelling Rant", "img": "systems/pf1/icons/items/inventory/scroll-magic.jpg", "documentCollection": "world.pf1-scrolls", "documentId": "4UMHoGPNuGyOx0ms", "flags": {}}, {"type": 2, "weight": 1, "range": [26, 26], "drawn": false, "text": "Scroll of Alter River", "img": "systems/pf1/icons/items/inventory/scroll-magic.jpg", "documentCollection": "world.pf1-scrolls", "documentId": "4Z9utrlNTVLlXo5A", "flags": {}}, {"type": 2, "weight": 1, "range": [27, 27], "drawn": false, "text": "Scroll of Major Creation", "img": "systems/pf1/icons/items/inventory/scroll-magic.jpg", "documentCollection": "world.pf1-scrolls", "documentId": "4jHSkEyiWU5aE4Zt", "flags": {}}, {"type": 2, "weight": 1, "range": [28, 28], "drawn": false, "text": "Scroll of Hunter's Blessing", "img": "systems/pf1/icons/items/inventory/scroll-magic.jpg", "documentCollection": "world.pf1-scrolls", "documentId": "57V9hpQd7GsAgBdH", "flags": {}}, {"type": 2, "weight": 1, "range": [29, 29], "drawn": false, "text": "Scroll of Foretell Failure", "img": "systems/pf1/icons/items/inventory/scroll-magic.jpg", "documentCollection": "world.pf1-scrolls", "documentId": "58hNLGAHtvwz00LS", "flags": {}}, {"type": 2, "weight": 1, "range": [30, 30], "drawn": false, "text": "Scroll of Monstrous Physique III", "img": "systems/pf1/icons/items/inventory/scroll-magic.jpg", "documentCollection": "world.pf1-scrolls", "documentId": "5Nke74QyOIevnkQm", "flags": {}}, {"type": 2, "weight": 1, "range": [31, 31], "drawn": false, "text": "Scroll of Elemental Body II", "img": "systems/pf1/icons/items/inventory/scroll-magic.jpg", "documentCollection": "world.pf1-scrolls", "documentId": "5XWGsjvqgxjQL6Xo", "flags": {}}, {"type": 2, "weight": 1, "range": [32, 32], "drawn": false, "text": "Scroll of Animal Growth", "img": "systems/pf1/icons/items/inventory/scroll-magic.jpg", "documentCollection": "world.pf1-scrolls", "documentId": "5eGKiLYvBSOKzDG3", "flags": {}}, {"type": 2, "weight": 1, "range": [33, 33], "drawn": false, "text": "Scroll of Righteous Might", "img": "systems/pf1/icons/items/inventory/scroll-magic.jpg", "documentCollection": "world.pf1-scrolls", "documentId": "5nf2FfME82dxwmfZ", "flags": {}}, {"type": 2, "weight": 1, "range": [34, 34], "drawn": false, "text": "Scroll of Deafening Song Bolt", "img": "systems/pf1/icons/items/inventory/scroll-magic.jpg", "documentCollection": "world.pf1-scrolls", "documentId": "5sOC5VHOy8HYcGTm", "flags": {}}, {"type": 2, "weight": 1, "range": [35, 35], "drawn": false, "text": "Scroll of Old Salt's Curse", "img": "systems/pf1/icons/items/inventory/scroll-magic.jpg", "documentCollection": "world.pf1-scrolls", "documentId": "64lelzmQpeztADUs", "flags": {}}, {"type": 2, "weight": 1, "range": [36, 36], "drawn": false, "text": "Scroll of Secret Chest", "img": "systems/pf1/icons/items/inventory/scroll-magic.jpg", "documentCollection": "world.pf1-scrolls", "documentId": "6A4RobnmgCRzNNlU", "flags": {}}, {"type": 2, "weight": 1, "range": [37, 37], "drawn": false, "text": "Scroll of Threefold Aspect", "img": "systems/pf1/icons/items/inventory/scroll-magic.jpg", "documentCollection": "world.pf1-scrolls", "documentId": "6CoMgRE7madvP6iC", "flags": {}}, {"type": 2, "weight": 1, "range": [38, 38], "drawn": false, "text": "Scroll of Erase Impressions", "img": "systems/pf1/icons/items/inventory/scroll-magic.jpg", "documentCollection": "world.pf1-scrolls", "documentId": "6H7Umb3lpsDfl2ev", "flags": {}}, {"type": 2, "weight": 1, "range": [39, 39], "drawn": false, "text": "Scroll of Unleash Pandemonium", "img": "systems/pf1/icons/items/inventory/scroll-magic.jpg", "documentCollection": "world.pf1-scrolls", "documentId": "6KiVroG5uVfkjnJs", "flags": {}}, {"type": 2, "weight": 1, "range": [40, 40], "drawn": false, "text": "Scroll of Possession Trap", "img": "systems/pf1/icons/items/inventory/scroll-magic.jpg", "documentCollection": "world.pf1-scrolls", "documentId": "6U1Z0h5FQhiK7Xc7", "flags": {}}, {"type": 2, "weight": 1, "range": [41, 41], "drawn": false, "text": "Scroll of Caustic Blood", "img": "systems/pf1/icons/items/inventory/scroll-magic.jpg", "documentCollection": "world.pf1-scrolls", "documentId": "6pX7ZzbUj4IY5IWw", "flags": {}}, {"type": 2, "weight": 1, "range": [42, 42], "drawn": false, "text": "Scroll of Aspect of the Wolf", "img": "systems/pf1/icons/items/inventory/scroll-magic.jpg", "documentCollection": "world.pf1-scrolls", "documentId": "6qvzLYgLnclT1wxA", "flags": {}}, {"type": 2, "weight": 1, "range": [43, 43], "drawn": false, "text": "Scroll of Contact Entity III", "img": "systems/pf1/icons/items/inventory/scroll-magic.jpg", "documentCollection": "world.pf1-scrolls", "documentId": "6sUA5rLhWRbvlIQp", "flags": {}}, {"type": 2, "weight": 1, "range": [44, 44], "drawn": false, "text": "Scroll of Wall of Ectoplasm", "img": "systems/pf1/icons/items/inventory/scroll-magic.jpg", "documentCollection": "world.pf1-scrolls", "documentId": "77udvBdrX9yXfs7d", "flags": {}}, {"type": 2, "weight": 1, "range": [45, 45], "drawn": false, "text": "Scroll of Rubberskin", "img": "systems/pf1/icons/items/inventory/scroll-magic.jpg", "documentCollection": "world.pf1-scrolls", "documentId": "7CE9kkW4xIdR1t0w", "flags": {}}, {"type": 2, "weight": 1, "range": [46, 46], "drawn": false, "text": "Scroll of Create Mindscape", "img": "systems/pf1/icons/items/inventory/scroll-magic.jpg", "documentCollection": "world.pf1-scrolls", "documentId": "7VCbHPeebo83zcHP", "flags": {}}, {"type": 2, "weight": 1, "range": [47, 47], "drawn": false, "text": "Scroll of Cloak of Shadows", "img": "systems/pf1/icons/items/inventory/scroll-magic.jpg", "documentCollection": "world.pf1-scrolls", "documentId": "7YuZRT7byEzhbZqa", "flags": {}}, {"type": 2, "weight": 1, "range": [48, 48], "drawn": false, "text": "Scroll of Red Hand of the Killer", "img": "systems/pf1/icons/items/inventory/scroll-magic.jpg", "documentCollection": "world.pf1-scrolls", "documentId": "7ce4vUBvDQPw2v2H", "flags": {}}, {"type": 2, "weight": 1, "range": [49, 49], "drawn": false, "text": "Scroll of Commune", "img": "systems/pf1/icons/items/inventory/scroll-magic.jpg", "documentCollection": "world.pf1-scrolls", "documentId": "7tzuQ2nI52dPn9Xu", "flags": {}}, {"type": 2, "weight": 1, "range": [50, 50], "drawn": false, "text": "Scroll of Disrupting Weapon", "img": "systems/pf1/icons/items/inventory/scroll-magic.jpg", "documentCollection": "world.pf1-scrolls", "documentId": "7v1tOALHBRieUMO5", "flags": {}}, {"type": 2, "weight": 1, "range": [51, 51], "drawn": false, "text": "Scroll of Charm Person, Mass", "img": "systems/pf1/icons/items/inventory/scroll-magic.jpg", "documentCollection": "world.pf1-scrolls", "documentId": "88LDEUj5wL8kVxM9", "flags": {}}, {"type": 2, "weight": 1, "range": [52, 52], "drawn": false, "text": "Scroll of Glimpse of Truth", "img": "systems/pf1/icons/items/inventory/scroll-magic.jpg", "documentCollection": "world.pf1-scrolls", "documentId": "8KQnpm7JqXqZuuBf", "flags": {}}, {"type": 2, "weight": 1, "range": [53, 53], "drawn": false, "text": "Scroll of Companion Transposition", "img": "systems/pf1/icons/items/inventory/scroll-magic.jpg", "documentCollection": "world.pf1-scrolls", "documentId": "8V9GTDLmBzgoGtz7", "flags": {}}, {"type": 2, "weight": 1, "range": [54, 54], "drawn": false, "text": "Scroll of Seeming", "img": "systems/pf1/icons/items/inventory/scroll-magic.jpg", "documentCollection": "world.pf1-scrolls", "documentId": "8WnkVc7yZB23EqsA", "flags": {}}, {"type": 2, "weight": 1, "range": [55, 55], "drawn": false, "text": "Scroll of Hold Monster", "img": "systems/pf1/icons/items/inventory/scroll-magic.jpg", "documentCollection": "world.pf1-scrolls", "documentId": "8ZFCwiS3fPT4XEGV", "flags": {}}, {"type": 2, "weight": 1, "range": [56, 56], "drawn": false, "text": "Scroll of Summoner Conduit", "img": "systems/pf1/icons/items/inventory/scroll-magic.jpg", "documentCollection": "world.pf1-scrolls", "documentId": "8aE5Gxuk32ju9Jdz", "flags": {}}, {"type": 2, "weight": 1, "range": [57, 57], "drawn": false, "text": "Scroll of Wall of Light", "img": "systems/pf1/icons/items/inventory/scroll-magic.jpg", "documentCollection": "world.pf1-scrolls", "documentId": "8kzjfxEFfq7qe7Kl", "flags": {}}, {"type": 2, "weight": 1, "range": [58, 58], "drawn": false, "text": "Scroll of Open Arms", "img": "systems/pf1/icons/items/inventory/scroll-magic.jpg", "documentCollection": "world.pf1-scrolls", "documentId": "9On4eXF9ggSnctMG", "flags": {}}, {"type": 2, "weight": 1, "range": [59, 59], "drawn": false, "text": "Scroll of Spell Immunity, Communal", "img": "systems/pf1/icons/items/inventory/scroll-magic.jpg", "documentCollection": "world.pf1-scrolls", "documentId": "9RtsUG3qauEeRL4K", "flags": {}}, {"type": 2, "weight": 1, "range": [60, 60], "drawn": false, "text": "Scroll of Nightmare", "img": "systems/pf1/icons/items/inventory/scroll-magic.jpg", "documentCollection": "world.pf1-scrolls", "documentId": "9dfUyEErT6tchcM3", "flags": {}}, {"type": 2, "weight": 1, "range": [61, 61], "drawn": false, "text": "Scroll of Blightburn Weapon", "img": "systems/pf1/icons/items/inventory/scroll-magic.jpg", "documentCollection": "world.pf1-scrolls", "documentId": "A5jc6IXXPrXLpGO3", "flags": {}}, {"type": 2, "weight": 1, "range": [62, 62], "drawn": false, "text": "Scroll of Release the Hounds", "img": "systems/pf1/icons/items/inventory/scroll-magic.jpg", "documentCollection": "world.pf1-scrolls", "documentId": "A9gBiAm59XViCTLr", "flags": {}}, {"type": 2, "weight": 1, "range": [63, 63], "drawn": false, "text": "Scroll of Fire Snake", "img": "systems/pf1/icons/items/inventory/scroll-magic.jpg", "documentCollection": "world.pf1-scrolls", "documentId": "AYEsVbaTaSgpJTUT", "flags": {}}, {"type": 2, "weight": 1, "range": [64, 64], "drawn": false, "text": "Scroll of Mask from Divination", "img": "systems/pf1/icons/items/inventory/scroll-magic.jpg", "documentCollection": "world.pf1-scrolls", "documentId": "AbHABe3NVAAMe8GX", "flags": {}}, {"type": 2, "weight": 1, "range": [65, 65], "drawn": false, "text": "Scroll of Reboot", "img": "systems/pf1/icons/items/inventory/scroll-magic.jpg", "documentCollection": "world.pf1-scrolls", "documentId": "AfRmeGKNdS0EYlG6", "flags": {}}, {"type": 2, "weight": 1, "range": [66, 66], "drawn": false, "text": "Scroll of Calm Air", "img": "systems/pf1/icons/items/inventory/scroll-magic.jpg", "documentCollection": "world.pf1-scrolls", "documentId": "Awd1ATEnSqHryFL5", "flags": {}}, {"type": 2, "weight": 1, "range": [67, 67], "drawn": false, "text": "Scroll of Slay Living", "img": "systems/pf1/icons/items/inventory/scroll-magic.jpg", "documentCollection": "world.pf1-scrolls", "documentId": "AyCnasNlr4fLmYu4", "flags": {}}, {"type": 2, "weight": 1, "range": [68, 68], "drawn": false, "text": "Scroll of Call Lightning Storm", "img": "systems/pf1/icons/items/inventory/scroll-magic.jpg", "documentCollection": "world.pf1-scrolls", "documentId": "B8UVSBDbKaSPRH1O", "flags": {}}, {"type": 2, "weight": 1, "range": [69, 69], "drawn": false, "text": "Scroll of Impossible Angles", "img": "systems/pf1/icons/items/inventory/scroll-magic.jpg", "documentCollection": "world.pf1-scrolls", "documentId": "Bdx5DPA94aFhBc3E", "flags": {}}, {"type": 2, "weight": 1, "range": [70, 70], "drawn": false, "text": "Scroll of Augmenting Wall", "img": "systems/pf1/icons/items/inventory/scroll-magic.jpg", "documentCollection": "world.pf1-scrolls", "documentId": "BgH7DwzbDbqGEVnX", "flags": {}}, {"type": 2, "weight": 1, "range": [71, 71], "drawn": false, "text": "Scroll of Sleepwalking Suggestion", "img": "systems/pf1/icons/items/inventory/scroll-magic.jpg", "documentCollection": "world.pf1-scrolls", "documentId": "BxHDFfZd80msdFUs", "flags": {}}, {"type": 2, "weight": 1, "range": [72, 72], "drawn": false, "text": "Scroll of Call Spirit", "img": "systems/pf1/icons/items/inventory/scroll-magic.jpg", "documentCollection": "world.pf1-scrolls", "documentId": "C4sH1GzaIFBcuXN0", "flags": {}}, {"type": 2, "weight": 1, "range": [73, 73], "drawn": false, "text": "Scroll of Trace Teleport", "img": "systems/pf1/icons/items/inventory/scroll-magic.jpg", "documentCollection": "world.pf1-scrolls", "documentId": "CR2BQz1dwuAvIqYJ", "flags": {}}, {"type": 2, "weight": 1, "range": [74, 74], "drawn": false, "text": "Scroll of Tidal Surge", "img": "systems/pf1/icons/items/inventory/scroll-magic.jpg", "documentCollection": "world.pf1-scrolls", "documentId": "CZvwpERkfNKNp0xC", "flags": {}}, {"type": 2, "weight": 1, "range": [75, 75], "drawn": false, "text": "Scroll of Deceptive Redundancy", "img": "systems/pf1/icons/items/inventory/scroll-magic.jpg", "documentCollection": "world.pf1-scrolls", "documentId": "CkejswCfuuq21OO5", "flags": {}}, {"type": 2, "weight": 1, "range": [76, 76], "drawn": false, "text": "Scroll of Runic Overload", "img": "systems/pf1/icons/items/inventory/scroll-magic.jpg", "documentCollection": "world.pf1-scrolls", "documentId": "D2qQLbb606mC28Td", "flags": {}}, {"type": 2, "weight": 1, "range": [77, 77], "drawn": false, "text": "Scroll of Castigate, Mass", "img": "systems/pf1/icons/items/inventory/scroll-magic.jpg", "documentCollection": "world.pf1-scrolls", "documentId": "DdwqnnXmnkNqioLv", "flags": {}}, {"type": 2, "weight": 1, "range": [78, 78], "drawn": false, "text": "Scroll of Army Across Time", "img": "systems/pf1/icons/items/inventory/scroll-magic.jpg", "documentCollection": "world.pf1-scrolls", "documentId": "DdxMfbNURRp3uELg", "flags": {}}, {"type": 2, "weight": 1, "range": [79, 79], "drawn": false, "text": "Scroll of Transplant Visage", "img": "systems/pf1/icons/items/inventory/scroll-magic.jpg", "documentCollection": "world.pf1-scrolls", "documentId": "Dkp2l9bdyjXYAUV9", "flags": {}}, {"type": 2, "weight": 1, "range": [80, 80], "drawn": false, "text": "Scroll of Sturdy Tree Fort", "img": "systems/pf1/icons/items/inventory/scroll-magic.jpg", "documentCollection": "world.pf1-scrolls", "documentId": "DmsRmUpooncAB06m", "flags": {}}, {"type": 2, "weight": 1, "range": [81, 81], "drawn": false, "text": "Scroll of Burst of Force", "img": "systems/pf1/icons/items/inventory/scroll-magic.jpg", "documentCollection": "world.pf1-scrolls", "documentId": "DqvmNUkA7Lzajeol", "flags": {}}, {"type": 2, "weight": 1, "range": [82, 82], "drawn": false, "text": "Scroll of Besmara's Grasping Depths", "img": "systems/pf1/icons/items/inventory/scroll-magic.jpg", "documentCollection": "world.pf1-scrolls", "documentId": "ECtbyuvN2b1AAZ8D", "flags": {}}, {"type": 2, "weight": 1, "range": [83, 83], "drawn": false, "text": "Scroll of Greater Reversion", "img": "systems/pf1/icons/items/inventory/scroll-magic.jpg", "documentCollection": "world.pf1-scrolls", "documentId": "EDdq6HY1Jx3ecJd0", "flags": {}}, {"type": 2, "weight": 1, "range": [84, 84], "drawn": false, "text": "Scroll of Lend Judgment, Greater", "img": "systems/pf1/icons/items/inventory/scroll-magic.jpg", "documentCollection": "world.pf1-scrolls", "documentId": "EG6fcCxSZTEj6JDT", "flags": {}}, {"type": 2, "weight": 1, "range": [85, 85], "drawn": false, "text": "Scroll of Feast on Fear", "img": "systems/pf1/icons/items/inventory/scroll-magic.jpg", "documentCollection": "world.pf1-scrolls", "documentId": "EH5VKc6T6p6jxUkh", "flags": {}}, {"type": 2, "weight": 1, "range": [86, 86], "drawn": false, "text": "Scroll of Hymn of Mercy", "img": "systems/pf1/icons/items/inventory/scroll-magic.jpg", "documentCollection": "world.pf1-scrolls", "documentId": "EjchQWDpdw2cYG3r", "flags": {}}, {"type": 2, "weight": 1, "range": [87, 87], "drawn": false, "text": "Scroll of Fable Tapestry", "img": "systems/pf1/icons/items/inventory/scroll-magic.jpg", "documentCollection": "world.pf1-scrolls", "documentId": "F4g52J0k2dr4o3fF", "flags": {}}, {"type": 2, "weight": 1, "range": [88, 88], "drawn": false, "text": "Scroll of Surface Excursion", "img": "systems/pf1/icons/items/inventory/scroll-magic.jpg", "documentCollection": "world.pf1-scrolls", "documentId": "FDjRCBn49vrULNtl", "flags": {}}, {"type": 2, "weight": 1, "range": [89, 89], "drawn": false, "text": "Scroll of Damnation Stride", "img": "systems/pf1/icons/items/inventory/scroll-magic.jpg", "documentCollection": "world.pf1-scrolls", "documentId": "FSSP85ufP96fx3b7", "flags": {}}, {"type": 2, "weight": 1, "range": [90, 90], "drawn": false, "text": "Scroll of Hallow", "img": "systems/pf1/icons/items/inventory/scroll-magic.jpg", "documentCollection": "world.pf1-scrolls", "documentId": "FjuYF03kB2xauUgL", "flags": {}}, {"type": 2, "weight": 1, "range": [91, 91], "drawn": false, "text": "Scroll of Teleport", "img": "systems/pf1/icons/items/inventory/scroll-magic.jpg", "documentCollection": "world.pf1-scrolls", "documentId": "FwQolzaC6KfhqYjt", "flags": {}}, {"type": 2, "weight": 1, "range": [92, 92], "drawn": false, "text": "Scroll of Grand Destiny", "img": "systems/pf1/icons/items/inventory/scroll-magic.jpg", "documentCollection": "world.pf1-scrolls", "documentId": "G1JFtHKLEZ55wvLl", "flags": {}}, {"type": 2, "weight": 1, "range": [93, 93], "drawn": false, "text": "Scroll of Dahak's Release", "img": "systems/pf1/icons/items/inventory/scroll-magic.jpg", "documentCollection": "world.pf1-scrolls", "documentId": "GDVbuRhN9O51gkjP", "flags": {}}, {"type": 2, "weight": 1, "range": [94, 94], "drawn": false, "text": "Scroll of Symbol of Scrying", "img": "systems/pf1/icons/items/inventory/scroll-magic.jpg", "documentCollection": "world.pf1-scrolls", "documentId": "GJ9mvILwXbQwSXQG", "flags": {}}, {"type": 2, "weight": 1, "range": [95, 95], "drawn": false, "text": "Scroll of Heretic's Tongue", "img": "systems/pf1/icons/items/inventory/scroll-magic.jpg", "documentCollection": "world.pf1-scrolls", "documentId": "GK7jvHgkJAZqGrON", "flags": {}}, {"type": 2, "weight": 1, "range": [96, 96], "drawn": false, "text": "Scroll of Arid Refuge", "img": "systems/pf1/icons/items/inventory/scroll-magic.jpg", "documentCollection": "world.pf1-scrolls", "documentId": "GSX4NjprNPrwnpjw", "flags": {}}, {"type": 2, "weight": 1, "range": [97, 97], "drawn": false, "text": "Scroll of Undead Anatomy II", "img": "systems/pf1/icons/items/inventory/scroll-magic.jpg", "documentCollection": "world.pf1-scrolls", "documentId": "GTzCNYX4SDZBJU2k", "flags": {}}, {"type": 2, "weight": 1, "range": [98, 98], "drawn": false, "text": "Scroll of Summon Lesser Demon", "img": "systems/pf1/icons/items/inventory/scroll-magic.jpg", "documentCollection": "world.pf1-scrolls", "documentId": "GhF69ypUUDfVM3u1", "flags": {}}, {"type": 2, "weight": 1, "range": [99, 99], "drawn": false, "text": "Scroll of Daywalker", "img": "systems/pf1/icons/items/inventory/scroll-magic.jpg", "documentCollection": "world.pf1-scrolls", "documentId": "GrVDA3SyRZiIZJ05", "flags": {}}, {"type": 2, "weight": 1, "range": [100, 100], "drawn": false, "text": "Scroll of Appearance of Life, Greater", "img": "systems/pf1/icons/items/inventory/scroll-magic.jpg", "documentCollection": "world.pf1-scrolls", "documentId": "H8N7pjsNDCB403Wr", "flags": {}}, {"type": 2, "weight": 1, "range": [101, 101], "drawn": false, "text": "Scroll of Darkvault", "img": "systems/pf1/icons/items/inventory/scroll-magic.jpg", "documentCollection": "world.pf1-scrolls", "documentId": "HCLZcQNmaUCab2KP", "flags": {}}, {"type": 2, "weight": 1, "range": [102, 102], "drawn": false, "text": "Scroll of Dissolution", "img": "systems/pf1/icons/items/inventory/scroll-magic.jpg", "documentCollection": "world.pf1-scrolls", "documentId": "HIFMVrLijcP9oeAP", "flags": {}}, {"type": 2, "weight": 1, "range": [103, 103], "drawn": false, "text": "Scroll of Whip of Centipedes", "img": "systems/pf1/icons/items/inventory/scroll-magic.jpg", "documentCollection": "world.pf1-scrolls", "documentId": "HmvI7TYKvgucB4xw", "flags": {}}, {"type": 2, "weight": 1, "range": [104, 104], "drawn": false, "text": "Scroll of Summon Kami", "img": "systems/pf1/icons/items/inventory/scroll-magic.jpg", "documentCollection": "world.pf1-scrolls", "documentId": "I9JzXPdoxnmQnLq9", "flags": {}}, {"type": 2, "weight": 1, "range": [105, 105], "drawn": false, "text": "Scroll of Hostile Juxtaposition", "img": "systems/pf1/icons/items/inventory/scroll-magic.jpg", "documentCollection": "world.pf1-scrolls", "documentId": "IRVu7uEUgiSelNPt", "flags": {}}, {"type": 2, "weight": 1, "range": [106, 106], "drawn": false, "text": "Scroll of Flame Strike", "img": "systems/pf1/icons/items/inventory/scroll-magic.jpg", "documentCollection": "world.pf1-scrolls", "documentId": "IVssRGIoFRVXxDeM", "flags": {}}, {"type": 2, "weight": 1, "range": [107, 107], "drawn": false, "text": "Scroll of Cone of Cold", "img": "systems/pf1/icons/items/inventory/scroll-magic.jpg", "documentCollection": "world.pf1-scrolls", "documentId": "IYKPpAkZPlxzUtXy", "flags": {}}, {"type": 2, "weight": 1, "range": [108, 108], "drawn": false, "text": "Scroll of Echolocation", "img": "systems/pf1/icons/items/inventory/scroll-magic.jpg", "documentCollection": "world.pf1-scrolls", "documentId": "IaZhjXJS5vvAF2tZ", "flags": {}}, {"type": 2, "weight": 1, "range": [109, 109], "drawn": false, "text": "Scroll of Acidic Spray", "img": "systems/pf1/icons/items/inventory/scroll-magic.jpg", "documentCollection": "world.pf1-scrolls", "documentId": "IwONbM7YTNSHlB0q", "flags": {}}, {"type": 2, "weight": 1, "range": [110, 110], "drawn": false, "text": "Scroll of Interposing Hand", "img": "systems/pf1/icons/items/inventory/scroll-magic.jpg", "documentCollection": "world.pf1-scrolls", "documentId": "IyzXxjGAYLPpouwy", "flags": {}}, {"type": 2, "weight": 1, "range": [111, 111], "drawn": false, "text": "Scroll of Telepathic Bond", "img": "systems/pf1/icons/items/inventory/scroll-magic.jpg", "documentCollection": "world.pf1-scrolls", "documentId": "IzYFfAxrZDaj2YGs", "flags": {}}, {"type": 2, "weight": 1, "range": [112, 112], "drawn": false, "text": "Scroll of Walk the Plank", "img": "systems/pf1/icons/items/inventory/scroll-magic.jpg", "documentCollection": "world.pf1-scrolls", "documentId": "JBOm57ywf6su0dID", "flags": {}}, {"type": 2, "weight": 1, "range": [113, 113], "drawn": false, "text": "Scroll of Burn Corruption", "img": "systems/pf1/icons/items/inventory/scroll-magic.jpg", "documentCollection": "world.pf1-scrolls", "documentId": "JCfBaPT5i8HV1aFH", "flags": {}}, {"type": 2, "weight": 1, "range": [114, 114], "drawn": false, "text": "Scroll of Straitjacket", "img": "systems/pf1/icons/items/inventory/scroll-magic.jpg", "documentCollection": "world.pf1-scrolls", "documentId": "JSPquRoJUiWDd5zg", "flags": {}}, {"type": 2, "weight": 1, "range": [115, 115], "drawn": false, "text": "Scroll of Repair Undead, Mass", "img": "systems/pf1/icons/items/inventory/scroll-magic.jpg", "documentCollection": "world.pf1-scrolls", "documentId": "JVcLwpejJmKmbAja", "flags": {}}, {"type": 2, "weight": 1, "range": [116, 116], "drawn": false, "text": "Scroll of Ethereal Envelope", "img": "systems/pf1/icons/items/inventory/scroll-magic.jpg", "documentCollection": "world.pf1-scrolls", "documentId": "JfxGfrFVDdNqTKuh", "flags": {}}, {"type": 2, "weight": 1, "range": [117, 117], "drawn": false, "text": "Scroll of Defensive Grace", "img": "systems/pf1/icons/items/inventory/scroll-magic.jpg", "documentCollection": "world.pf1-scrolls", "documentId": "JsWaCVtY9sSZp19h", "flags": {}}, {"type": 2, "weight": 1, "range": [118, 118], "drawn": false, "text": "Scroll of Intellect Fortress II", "img": "systems/pf1/icons/items/inventory/scroll-magic.jpg", "documentCollection": "world.pf1-scrolls", "documentId": "JwlSqsgtU6BRn4AU", "flags": {}}, {"type": 2, "weight": 1, "range": [119, 119], "drawn": false, "text": "Scroll of Astral Projection, Lesser", "img": "systems/pf1/icons/items/inventory/scroll-magic.jpg", "documentCollection": "world.pf1-scrolls", "documentId": "JzjXvj5cL8QUGkiI", "flags": {}}, {"type": 2, "weight": 1, "range": [120, 120], "drawn": false, "text": "Scroll of Banish Seeming", "img": "systems/pf1/icons/items/inventory/scroll-magic.jpg", "documentCollection": "world.pf1-scrolls", "documentId": "KBIx38SUCkzHgAkx", "flags": {}}, {"type": 2, "weight": 1, "range": [121, 121], "drawn": false, "text": "Scroll of Seek Shelter", "img": "systems/pf1/icons/items/inventory/scroll-magic.jpg", "documentCollection": "world.pf1-scrolls", "documentId": "KQHRkw1GTHrgec1l", "flags": {}}, {"type": 2, "weight": 1, "range": [122, 122], "drawn": false, "text": "Scroll of Raise Dead", "img": "systems/pf1/icons/items/inventory/scroll-magic.jpg", "documentCollection": "world.pf1-scrolls", "documentId": "KuEOwRjyW5xjiGDH", "flags": {}}, {"type": 2, "weight": 1, "range": [123, 123], "drawn": false, "text": "Scroll of Mage's Faithful Hound", "img": "systems/pf1/icons/items/inventory/scroll-magic.jpg", "documentCollection": "world.pf1-scrolls", "documentId": "L2pWWQgHZP1Dk0vq", "flags": {}}, {"type": 2, "weight": 1, "range": [124, 124], "drawn": false, "text": "Scroll of Air Walk, Communal", "img": "systems/pf1/icons/items/inventory/scroll-magic.jpg", "documentCollection": "world.pf1-scrolls", "documentId": "LBftJH7v6n3aHNbx", "flags": {}}, {"type": 2, "weight": 1, "range": [125, 125], "drawn": false, "text": "Scroll of Debilitating Pain, Mass", "img": "systems/pf1/icons/items/inventory/scroll-magic.jpg", "documentCollection": "world.pf1-scrolls", "documentId": "LC3UJoVwVK8CmriU", "flags": {}}, {"type": 2, "weight": 1, "range": [126, 126], "drawn": false, "text": "Scroll of Telekinesis", "img": "systems/pf1/icons/items/inventory/scroll-magic.jpg", "documentCollection": "world.pf1-scrolls", "documentId": "LI0bwNBcZSaoGl5K", "flags": {}}, {"type": 2, "weight": 1, "range": [127, 127], "drawn": false, "text": "Scroll of Steal Years, Greater", "img": "systems/pf1/icons/items/inventory/scroll-magic.jpg", "documentCollection": "world.pf1-scrolls", "documentId": "LTrUn8KUOEFl1e6Z", "flags": {}}, {"type": 2, "weight": 1, "range": [128, 128], "drawn": false, "text": "Scroll of Heroic Fortune, Mass", "img": "systems/pf1/icons/items/inventory/scroll-magic.jpg", "documentCollection": "world.pf1-scrolls", "documentId": "LVGy3PVeDpxTKVaL", "flags": {}}, {"type": 2, "weight": 1, "range": [129, 129], "drawn": false, "text": "Scroll of Strip Scales", "img": "systems/pf1/icons/items/inventory/scroll-magic.jpg", "documentCollection": "world.pf1-scrolls", "documentId": "MEKOUBN1F1sAiSH9", "flags": {}}, {"type": 2, "weight": 1, "range": [130, 130], "drawn": false, "text": "Scroll of Sun's Disdain, Mass", "img": "systems/pf1/icons/items/inventory/scroll-magic.jpg", "documentCollection": "world.pf1-scrolls", "documentId": "MJj2NuwWTtv1Mel4", "flags": {}}, {"type": 2, "weight": 1, "range": [131, 131], "drawn": false, "text": "Scroll of Life Conduit, Greater", "img": "systems/pf1/icons/items/inventory/scroll-magic.jpg", "documentCollection": "world.pf1-scrolls", "documentId": "MXpHtxMOTFtnG2ge", "flags": {}}, {"type": 2, "weight": 1, "range": [132, 132], "drawn": false, "text": "Scroll of Steal Power", "img": "systems/pf1/icons/items/inventory/scroll-magic.jpg", "documentCollection": "world.pf1-scrolls", "documentId": "McGiFIoUvoqBA53R", "flags": {}}, {"type": 2, "weight": 1, "range": [133, 133], "drawn": false, "text": "Scroll of Contact Other Plane", "img": "systems/pf1/icons/items/inventory/scroll-magic.jpg", "documentCollection": "world.pf1-scrolls", "documentId": "MtfdH4iKwcaMFYD0", "flags": {}}, {"type": 2, "weight": 1, "range": [134, 134], "drawn": false, "text": "Scroll of Breath of Life", "img": "systems/pf1/icons/items/inventory/scroll-magic.jpg", "documentCollection": "world.pf1-scrolls", "documentId": "MuExdH6BtYIeHvL9", "flags": {}}, {"type": 2, "weight": 1, "range": [135, 135], "drawn": false, "text": "Scroll of Dungeonsight", "img": "systems/pf1/icons/items/inventory/scroll-magic.jpg", "documentCollection": "world.pf1-scrolls", "documentId": "N0UNgpo3BTPq3KlV", "flags": {}}, {"type": 2, "weight": 1, "range": [136, 136], "drawn": false, "text": "Scroll of Bolts of Bedevilment", "img": "systems/pf1/icons/items/inventory/scroll-magic.jpg", "documentCollection": "world.pf1-scrolls", "documentId": "N1UnJGXdtWGerW2h", "flags": {}}, {"type": 2, "weight": 1, "range": [137, 137], "drawn": false, "text": "Scroll of Hammer of Mending", "img": "systems/pf1/icons/items/inventory/scroll-magic.jpg", "documentCollection": "world.pf1-scrolls", "documentId": "OK7Aq8eYt7PakN51", "flags": {}}, {"type": 2, "weight": 1, "range": [138, 138], "drawn": false, "text": "Scroll of Command, Greater", "img": "systems/pf1/icons/items/inventory/scroll-magic.jpg", "documentCollection": "world.pf1-scrolls", "documentId": "OWRVC9kqWkv6r0st", "flags": {}}, {"type": 2, "weight": 1, "range": [139, 139], "drawn": false, "text": "Scroll of Gravity Well", "img": "systems/pf1/icons/items/inventory/scroll-magic.jpg", "documentCollection": "world.pf1-scrolls", "documentId": "OZYVIDSkNw4lLaMV", "flags": {}}, {"type": 2, "weight": 1, "range": [140, 140], "drawn": false, "text": "Scroll of Vengeful Stinger", "img": "systems/pf1/icons/items/inventory/scroll-magic.jpg", "documentCollection": "world.pf1-scrolls", "documentId": "OZz0uGAKCxZCO3BH", "flags": {}}, {"type": 2, "weight": 1, "range": [141, 141], "drawn": false, "text": "Scroll of Pillar of Life", "img": "systems/pf1/icons/items/inventory/scroll-magic.jpg", "documentCollection": "world.pf1-scrolls", "documentId": "ObQSzLqkWF3yc0fh", "flags": {}}, {"type": 2, "weight": 1, "range": [142, 142], "drawn": false, "text": "Scroll of Sanctify Weapons", "img": "systems/pf1/icons/items/inventory/scroll-magic.jpg", "documentCollection": "world.pf1-scrolls", "documentId": "Oi57nf3HJOoKqLSD", "flags": {}}, {"type": 2, "weight": 1, "range": [143, 143], "drawn": false, "text": "Scroll of Delayed Consumption", "img": "systems/pf1/icons/items/inventory/scroll-magic.jpg", "documentCollection": "world.pf1-scrolls", "documentId": "OxjMb1SiW4AcBCpm", "flags": {}}, {"type": 2, "weight": 1, "range": [144, 144], "drawn": false, "text": "Scroll of Pessimism", "img": "systems/pf1/icons/items/inventory/scroll-magic.jpg", "documentCollection": "world.pf1-scrolls", "documentId": "P83stIEaPsP4nhEz", "flags": {}}, {"type": 2, "weight": 1, "range": [145, 145], "drawn": false, "text": "Scroll of Die for Your Master", "img": "systems/pf1/icons/items/inventory/scroll-magic.jpg", "documentCollection": "world.pf1-scrolls", "documentId": "PGbxJ3Enx87CpWe1", "flags": {}}, {"type": 2, "weight": 1, "range": [146, 146], "drawn": false, "text": "Scroll of Song of Discord", "img": "systems/pf1/icons/items/inventory/scroll-magic.jpg", "documentCollection": "world.pf1-scrolls", "documentId": "PR0XhCP4ZcE4spmr", "flags": {}}, {"type": 2, "weight": 1, "range": [147, 147], "drawn": false, "text": "Scroll of Blood Tentacles", "img": "systems/pf1/icons/items/inventory/scroll-magic.jpg", "documentCollection": "world.pf1-scrolls", "documentId": "PojpjsiPExKo2Z3n", "flags": {}}, {"type": 2, "weight": 1, "range": [148, 148], "drawn": false, "text": "Scroll of Spellcasting Contract, Lesser", "img": "systems/pf1/icons/items/inventory/scroll-magic.jpg", "documentCollection": "world.pf1-scrolls", "documentId": "PueRh1EHSeJgwfyn", "flags": {}}, {"type": 2, "weight": 1, "range": [149, 149], "drawn": false, "text": "Scroll of Cure Light Wounds, Mass", "img": "systems/pf1/icons/items/inventory/scroll-magic.jpg", "documentCollection": "world.pf1-scrolls", "documentId": "PycQAHXBZyZTD1we", "flags": {}}, {"type": 2, "weight": 1, "range": [150, 150], "drawn": false, "text": "Scroll of Rapid Repair", "img": "systems/pf1/icons/items/inventory/scroll-magic.jpg", "documentCollection": "world.pf1-scrolls", "documentId": "Q9PhLleUCsngZTU9", "flags": {}}, {"type": 2, "weight": 1, "range": [151, 151], "drawn": false, "text": "Scroll of Siphon Magic", "img": "systems/pf1/icons/items/inventory/scroll-magic.jpg", "documentCollection": "world.pf1-scrolls", "documentId": "QJzR26TGSDjvFCVG", "flags": {}}, {"type": 2, "weight": 1, "range": [152, 152], "drawn": false, "text": "Scroll of Persistent Image", "img": "systems/pf1/icons/items/inventory/scroll-magic.jpg", "documentCollection": "world.pf1-scrolls", "documentId": "QUryERS2yIpChRgs", "flags": {}}, {"type": 2, "weight": 1, "range": [153, 153], "drawn": false, "text": "Scroll of Slough", "img": "systems/pf1/icons/items/inventory/scroll-magic.jpg", "documentCollection": "world.pf1-scrolls", "documentId": "QZGw2xu9o8KWnOpo", "flags": {}}, {"type": 2, "weight": 1, "range": [154, 154], "drawn": false, "text": "Scroll of Duplicate Familiar", "img": "systems/pf1/icons/items/inventory/scroll-magic.jpg", "documentCollection": "world.pf1-scrolls", "documentId": "QfIuY3rytStlOvFc", "flags": {}}, {"type": 2, "weight": 1, "range": [155, 155], "drawn": false, "text": "Scroll of Naga Shape II", "img": "systems/pf1/icons/items/inventory/scroll-magic.jpg", "documentCollection": "world.pf1-scrolls", "documentId": "QlDWVXlO4tAInkuJ", "flags": {}}, {"type": 2, "weight": 1, "range": [156, 156], "drawn": false, "text": "Scroll of Mental Barrier IV", "img": "systems/pf1/icons/items/inventory/scroll-magic.jpg", "documentCollection": "world.pf1-scrolls", "documentId": "QvLiPnOh1ZU7DAL8", "flags": {}}, {"type": 2, "weight": 1, "range": [157, 157], "drawn": false, "text": "Scroll of Blight", "img": "systems/pf1/icons/items/inventory/scroll-magic.jpg", "documentCollection": "world.pf1-scrolls", "documentId": "RDtUdBircCISvN6N", "flags": {}}, {"type": 2, "weight": 1, "range": [158, 158], "drawn": false, "text": "Scroll of Elude Time", "img": "systems/pf1/icons/items/inventory/scroll-magic.jpg", "documentCollection": "world.pf1-scrolls", "documentId": "RH0zmh5hJqZyzwUl", "flags": {}}, {"type": 2, "weight": 1, "range": [159, 159], "drawn": false, "text": "Scroll of Dispel Good", "img": "systems/pf1/icons/items/inventory/scroll-magic.jpg", "documentCollection": "world.pf1-scrolls", "documentId": "RKyatf7oJ181vE30", "flags": {}}, {"type": 2, "weight": 1, "range": [160, 160], "drawn": false, "text": "Scroll of Ban Corruption", "img": "systems/pf1/icons/items/inventory/scroll-magic.jpg", "documentCollection": "world.pf1-scrolls", "documentId": "RLrOEQwCf5keEubG", "flags": {}}, {"type": 2, "weight": 1, "range": [161, 161], "drawn": false, "text": "Scroll of Magic Jar", "img": "systems/pf1/icons/items/inventory/scroll-magic.jpg", "documentCollection": "world.pf1-scrolls", "documentId": "RgyExbOtriz5WG1I", "flags": {}}, {"type": 2, "weight": 1, "range": [162, 162], "drawn": false, "text": "Scroll of Cleanse", "img": "systems/pf1/icons/items/inventory/scroll-magic.jpg", "documentCollection": "world.pf1-scrolls", "documentId": "RiEaY9wuYXK17jMj", "flags": {}}, {"type": 2, "weight": 1, "range": [163, 163], "drawn": false, "text": "Scroll of Beast Shape III", "img": "systems/pf1/icons/items/inventory/scroll-magic.jpg", "documentCollection": "world.pf1-scrolls", "documentId": "S268OvIvbfxYUAKT", "flags": {}}, {"type": 2, "weight": 1, "range": [164, 164], "drawn": false, "text": "Scroll of Transmute Rock to Mud", "img": "systems/pf1/icons/items/inventory/scroll-magic.jpg", "documentCollection": "world.pf1-scrolls", "documentId": "SPipzJz8wVvJk4uU", "flags": {}}, {"type": 2, "weight": 1, "range": [165, 165], "drawn": false, "text": "Scroll of Callback, Greater", "img": "systems/pf1/icons/items/inventory/scroll-magic.jpg", "documentCollection": "world.pf1-scrolls", "documentId": "SQwtpd2G8AYqSJ4Q", "flags": {}}, {"type": 2, "weight": 1, "range": [166, 166], "drawn": false, "text": "Scroll of Mage's Private Sanctum", "img": "systems/pf1/icons/items/inventory/scroll-magic.jpg", "documentCollection": "world.pf1-scrolls", "documentId": "SYy61eNh27ZACkWc", "flags": {}}, {"type": 2, "weight": 1, "range": [167, 167], "drawn": false, "text": "Scroll of Spell Absorption", "img": "systems/pf1/icons/items/inventory/scroll-magic.jpg", "documentCollection": "world.pf1-scrolls", "documentId": "SZpJs3p9HvAfk2rz", "flags": {}}, {"type": 2, "weight": 1, "range": [168, 168], "drawn": false, "text": "Scroll of Contagious Suggestion", "img": "systems/pf1/icons/items/inventory/scroll-magic.jpg", "documentCollection": "world.pf1-scrolls", "documentId": "SbW5kThXE5cMkrHC", "flags": {}}, {"type": 2, "weight": 1, "range": [169, 169], "drawn": false, "text": "Scroll of Bladed Dash, Greater", "img": "systems/pf1/icons/items/inventory/scroll-magic.jpg", "documentCollection": "world.pf1-scrolls", "documentId": "SwXMGcfSIIsvCYA7", "flags": {}}, {"type": 2, "weight": 1, "range": [170, 170], "drawn": false, "text": "Scroll of Grease, Greater", "img": "systems/pf1/icons/items/inventory/scroll-magic.jpg", "documentCollection": "world.pf1-scrolls", "documentId": "T39xFGldmzBGGmYu", "flags": {}}, {"type": 2, "weight": 1, "range": [171, 171], "drawn": false, "text": "Scroll of Repress Memory", "img": "systems/pf1/icons/items/inventory/scroll-magic.jpg", "documentCollection": "world.pf1-scrolls", "documentId": "T7RCKxjw3REclCtp", "flags": {}}, {"type": 2, "weight": 1, "range": [172, 172], "drawn": false, "text": "Scroll of Cave Fangs", "img": "systems/pf1/icons/items/inventory/scroll-magic.jpg", "documentCollection": "world.pf1-scrolls", "documentId": "TDhNwyvqB7u3iH97", "flags": {}}, {"type": 2, "weight": 1, "range": [173, 173], "drawn": false, "text": "Scroll of Wind Blades", "img": "systems/pf1/icons/items/inventory/scroll-magic.jpg", "documentCollection": "world.pf1-scrolls", "documentId": "TGA9DFJHuXKl9mjy", "flags": {}}, {"type": 2, "weight": 1, "range": [174, 174], "drawn": false, "text": "Scroll of Soothe Construct", "img": "systems/pf1/icons/items/inventory/scroll-magic.jpg", "documentCollection": "world.pf1-scrolls", "documentId": "TRRcDZtaAHW259cj", "flags": {}}, {"type": 2, "weight": 1, "range": [175, 175], "drawn": false, "text": "Scroll of Vile Dog Transformation", "img": "systems/pf1/icons/items/inventory/scroll-magic.jpg", "documentCollection": "world.pf1-scrolls", "documentId": "TSXB2eRUc12UB3C8", "flags": {}}, {"type": 2, "weight": 1, "range": [176, 176], "drawn": false, "text": "Scroll of Remote Viewing", "img": "systems/pf1/icons/items/inventory/scroll-magic.jpg", "documentCollection": "world.pf1-scrolls", "documentId": "TVgnqQBGTP9QZr0y", "flags": {}}, {"type": 2, "weight": 1, "range": [177, 177], "drawn": false, "text": "Scroll of Symbol of Striking", "img": "systems/pf1/icons/items/inventory/scroll-magic.jpg", "documentCollection": "world.pf1-scrolls", "documentId": "ThJQGAv5BFV91Hcl", "flags": {}}, {"type": 2, "weight": 1, "range": [178, 178], "drawn": false, "text": "Scroll of Cold Iron Fetters", "img": "systems/pf1/icons/items/inventory/scroll-magic.jpg", "documentCollection": "world.pf1-scrolls", "documentId": "TqmLro867Z2DVGNE", "flags": {}}, {"type": 2, "weight": 1, "range": [179, 179], "drawn": false, "text": "Scroll of Geniekind", "img": "systems/pf1/icons/items/inventory/scroll-magic.jpg", "documentCollection": "world.pf1-scrolls", "documentId": "TtR3lGZ6USAkLtnz", "flags": {}}, {"type": 2, "weight": 1, "range": [180, 180], "drawn": false, "text": "Scroll of Black Spot", "img": "systems/pf1/icons/items/inventory/scroll-magic.jpg", "documentCollection": "world.pf1-scrolls", "documentId": "ULwJZEBRm3MawCD9", "flags": {}}, {"type": 2, "weight": 1, "range": [181, 181], "drawn": false, "text": "Scroll of Befuddled Combatant", "img": "systems/pf1/icons/items/inventory/scroll-magic.jpg", "documentCollection": "world.pf1-scrolls", "documentId": "UZoywQhVzUigqsWO", "flags": {}}, {"type": 2, "weight": 1, "range": [182, 182], "drawn": false, "text": "Scroll of Hex Glyph, Greater", "img": "systems/pf1/icons/items/inventory/scroll-magic.jpg", "documentCollection": "world.pf1-scrolls", "documentId": "UhDu9GPwlyuuaKxv", "flags": {}}, {"type": 2, "weight": 1, "range": [183, 183], "drawn": false, "text": "Scroll of Oneiric Horror, Greater", "img": "systems/pf1/icons/items/inventory/scroll-magic.jpg", "documentCollection": "world.pf1-scrolls", "documentId": "UhmNy7gvQRAQTDUz", "flags": {}}, {"type": 2, "weight": 1, "range": [184, 184], "drawn": false, "text": "Scroll of Tree Stride", "img": "systems/pf1/icons/items/inventory/scroll-magic.jpg", "documentCollection": "world.pf1-scrolls", "documentId": "UtCJUF9YT4WumJYf", "flags": {}}, {"type": 2, "weight": 1, "range": [185, 185], "drawn": false, "text": "Scroll of Wall of Sound", "img": "systems/pf1/icons/items/inventory/scroll-magic.jpg", "documentCollection": "world.pf1-scrolls", "documentId": "UtuYoscntP3LdOKc", "flags": {}}, {"type": 2, "weight": 1, "range": [186, 186], "drawn": false, "text": "Scroll of Baleful Polymorph", "img": "systems/pf1/icons/items/inventory/scroll-magic.jpg", "documentCollection": "world.pf1-scrolls", "documentId": "VEUUyS4E36idV7V6", "flags": {}}, {"type": 2, "weight": 1, "range": [187, 187], "drawn": false, "text": "Scroll of Mark of Justice", "img": "systems/pf1/icons/items/inventory/scroll-magic.jpg", "documentCollection": "world.pf1-scrolls", "documentId": "VFGsG8EQUGW9idBN", "flags": {}}, {"type": 2, "weight": 1, "range": [188, 188], "drawn": false, "text": "Scroll of Mind Fog", "img": "systems/pf1/icons/items/inventory/scroll-magic.jpg", "documentCollection": "world.pf1-scrolls", "documentId": "VJSIltlec7i8wg7w", "flags": {}}, {"type": 2, "weight": 1, "range": [189, 189], "drawn": false, "text": "Scroll of Flexile Curse", "img": "systems/pf1/icons/items/inventory/scroll-magic.jpg", "documentCollection": "world.pf1-scrolls", "documentId": "VSqsIbaOWzpdedz5", "flags": {}}, {"type": 2, "weight": 1, "range": [190, 190], "drawn": false, "text": "Scroll of Holy Ice", "img": "systems/pf1/icons/items/inventory/scroll-magic.jpg", "documentCollection": "world.pf1-scrolls", "documentId": "VqzwAVtM2oIp8fQS", "flags": {}}, {"type": 2, "weight": 1, "range": [191, 191], "drawn": false, "text": "Scroll of Passwall", "img": "systems/pf1/icons/items/inventory/scroll-magic.jpg", "documentCollection": "world.pf1-scrolls", "documentId": "VsrmedpZBJ9j0R4s", "flags": {}}, {"type": 2, "weight": 1, "range": [192, 192], "drawn": false, "text": "Scroll of Ancestral Memory", "img": "systems/pf1/icons/items/inventory/scroll-magic.jpg", "documentCollection": "world.pf1-scrolls", "documentId": "W27kRgAUM1uBbaV5", "flags": {}}, {"type": 2, "weight": 1, "range": [193, 193], "drawn": false, "text": "Scroll of Stunning Finale", "img": "systems/pf1/icons/items/inventory/scroll-magic.jpg", "documentCollection": "world.pf1-scrolls", "documentId": "X4kjhyXjJneShRS9", "flags": {}}, {"type": 2, "weight": 1, "range": [194, 194], "drawn": false, "text": "Scroll of Locate Gate", "img": "systems/pf1/icons/items/inventory/scroll-magic.jpg", "documentCollection": "world.pf1-scrolls", "documentId": "XFbA4f5v4yUytAEv", "flags": {}}, {"type": 2, "weight": 1, "range": [195, 195], "drawn": false, "text": "Scroll of Fabricate", "img": "systems/pf1/icons/items/inventory/scroll-magic.jpg", "documentCollection": "world.pf1-scrolls", "documentId": "Xe2oI5DlyWfMseQW", "flags": {}}, {"type": 2, "weight": 1, "range": [196, 196], "drawn": false, "text": "Scroll of Rune of Ruin", "img": "systems/pf1/icons/items/inventory/scroll-magic.jpg", "documentCollection": "world.pf1-scrolls", "documentId": "Xhrpig4DdCYSVGkb", "flags": {}}, {"type": 2, "weight": 1, "range": [197, 197], "drawn": false, "text": "Scroll of Apathy", "img": "systems/pf1/icons/items/inventory/scroll-magic.jpg", "documentCollection": "world.pf1-scrolls", "documentId": "XkWyrdvNiH0SnCMY", "flags": {}}, {"type": 2, "weight": 1, "range": [198, 198], "drawn": false, "text": "Scroll of Etheric Shards", "img": "systems/pf1/icons/items/inventory/scroll-magic.jpg", "documentCollection": "world.pf1-scrolls", "documentId": "XvVMsEn4zWEyOCB0", "flags": {}}, {"type": 2, "weight": 1, "range": [199, 199], "drawn": false, "text": "Scroll of Sacred Nimbus", "img": "systems/pf1/icons/items/inventory/scroll-magic.jpg", "documentCollection": "world.pf1-scrolls", "documentId": "Y2vsRQBLqt0ek1O3", "flags": {}}, {"type": 2, "weight": 1, "range": [200, 200], "drawn": false, "text": "Scroll of Parchment Swarm", "img": "systems/pf1/icons/items/inventory/scroll-magic.jpg", "documentCollection": "world.pf1-scrolls", "documentId": "Y49vhEC46jyfHCPy", "flags": {}}, {"type": 2, "weight": 1, "range": [201, 201], "drawn": false, "text": "Scroll of Forbid Action, Greater", "img": "systems/pf1/icons/items/inventory/scroll-magic.jpg", "documentCollection": "world.pf1-scrolls", "documentId": "Y4s3OBRtwJkr85TK", "flags": {}}, {"type": 2, "weight": 1, "range": [202, 202], "drawn": false, "text": "Scroll of Torpid Reanimation", "img": "systems/pf1/icons/items/inventory/scroll-magic.jpg", "documentCollection": "world.pf1-scrolls", "documentId": "Y6c2tC0s3hIKd9Gl", "flags": {}}, {"type": 2, "weight": 1, "range": [203, 203], "drawn": false, "text": "Scroll of Atonement", "img": "systems/pf1/icons/items/inventory/scroll-magic.jpg", "documentCollection": "world.pf1-scrolls", "documentId": "YAT3aPl9L8HHdW02", "flags": {}}, {"type": 2, "weight": 1, "range": [204, 204], "drawn": false, "text": "Scroll of Conditional Curse", "img": "systems/pf1/icons/items/inventory/scroll-magic.jpg", "documentCollection": "world.pf1-scrolls", "documentId": "YDO8cJbsUK3v1jCM", "flags": {}}, {"type": 2, "weight": 1, "range": [205, 205], "drawn": false, "text": "Scroll of Break Enchantment", "img": "systems/pf1/icons/items/inventory/scroll-magic.jpg", "documentCollection": "world.pf1-scrolls", "documentId": "YXVQewVloXL7usKm", "flags": {}}, {"type": 2, "weight": 1, "range": [206, 206], "drawn": false, "text": "Scroll of Shadowbard", "img": "systems/pf1/icons/items/inventory/scroll-magic.jpg", "documentCollection": "world.pf1-scrolls", "documentId": "YbKaLB9pBrWkCBt7", "flags": {}}, {"type": 2, "weight": 1, "range": [207, 207], "drawn": false, "text": "Scroll of Energy Siege Shot", "img": "systems/pf1/icons/items/inventory/scroll-magic.jpg", "documentCollection": "world.pf1-scrolls", "documentId": "YbjVLabr44YCdQfj", "flags": {}}, {"type": 2, "weight": 1, "range": [208, 208], "drawn": false, "text": "Scroll of Animus Mine, Greater", "img": "systems/pf1/icons/items/inventory/scroll-magic.jpg", "documentCollection": "world.pf1-scrolls", "documentId": "ZC66Jtseu6txXHxm", "flags": {}}, {"type": 2, "weight": 1, "range": [209, 209], "drawn": false, "text": "Scroll of Mind Probe", "img": "systems/pf1/icons/items/inventory/scroll-magic.jpg", "documentCollection": "world.pf1-scrolls", "documentId": "ZFLn48MkC8W7Fqvk", "flags": {}}, {"type": 2, "weight": 1, "range": [210, 210], "drawn": false, "text": "Scroll of Prying Eyes", "img": "systems/pf1/icons/items/inventory/scroll-magic.jpg", "documentCollection": "world.pf1-scrolls", "documentId": "ZHlkZpluKEurr4jP", "flags": {}}, {"type": 2, "weight": 1, "range": [211, 211], "drawn": false, "text": "Scroll of Commune with Plane", "img": "systems/pf1/icons/items/inventory/scroll-magic.jpg", "documentCollection": "world.pf1-scrolls", "documentId": "ZLKpqc7GTr7U8o1n", "flags": {}}, {"type": 2, "weight": 1, "range": [212, 212], "drawn": false, "text": "Scroll of Suffocation", "img": "systems/pf1/icons/items/inventory/scroll-magic.jpg", "documentCollection": "world.pf1-scrolls", "documentId": "Zbx9oj81LWhrhr4g", "flags": {}}, {"type": 2, "weight": 1, "range": [213, 213], "drawn": false, "text": "Scroll of False Future", "img": "systems/pf1/icons/items/inventory/scroll-magic.jpg", "documentCollection": "world.pf1-scrolls", "documentId": "ZnXFEICgMT6LQeJU", "flags": {}}, {"type": 2, "weight": 1, "range": [214, 214], "drawn": false, "text": "Scroll of Thoughtsense", "img": "systems/pf1/icons/items/inventory/scroll-magic.jpg", "documentCollection": "world.pf1-scrolls", "documentId": "Zy1DAePgXk5SqCq8", "flags": {}}, {"type": 2, "weight": 1, "range": [215, 215], "drawn": false, "text": "Scroll of Carve Passage", "img": "systems/pf1/icons/items/inventory/scroll-magic.jpg", "documentCollection": "world.pf1-scrolls", "documentId": "aFfAmbzXp0Jl8y84", "flags": {}}, {"type": 2, "weight": 1, "range": [216, 216], "drawn": false, "text": "Scroll of Languid Bomb Admixture", "img": "systems/pf1/icons/items/inventory/scroll-magic.jpg", "documentCollection": "world.pf1-scrolls", "documentId": "aMwYmF1mPgo3QSUz", "flags": {}}, {"type": 2, "weight": 1, "range": [217, 217], "drawn": false, "text": "Scroll of Sending", "img": "systems/pf1/icons/items/inventory/scroll-magic.jpg", "documentCollection": "world.pf1-scrolls", "documentId": "abjWUWAietZGbbg7", "flags": {}}, {"type": 2, "weight": 1, "range": [218, 218], "drawn": false, "text": "Scroll of Cacophonous Call, Mass", "img": "systems/pf1/icons/items/inventory/scroll-magic.jpg", "documentCollection": "world.pf1-scrolls", "documentId": "ae56xh5RObiF9U1r", "flags": {}}, {"type": 2, "weight": 1, "range": [219, 219], "drawn": false, "text": "Scroll of Wracking Ray", "img": "systems/pf1/icons/items/inventory/scroll-magic.jpg", "documentCollection": "world.pf1-scrolls", "documentId": "bTq9SwsdW0XJ3eQZ", "flags": {}}, {"type": 2, "weight": 1, "range": [220, 220], "drawn": false, "text": "Scroll of Summon Lesser Psychopomp", "img": "systems/pf1/icons/items/inventory/scroll-magic.jpg", "documentCollection": "world.pf1-scrolls", "documentId": "bdXX5TfcDkgghhpj", "flags": {}}, {"type": 2, "weight": 1, "range": [221, 221], "drawn": false, "text": "Scroll of Summon Genie", "img": "systems/pf1/icons/items/inventory/scroll-magic.jpg", "documentCollection": "world.pf1-scrolls", "documentId": "cb54SM7OcT9QPNUX", "flags": {}}, {"type": 2, "weight": 1, "range": [222, 222], "drawn": false, "text": "Scroll of Respectful Quiet", "img": "systems/pf1/icons/items/inventory/scroll-magic.jpg", "documentCollection": "world.pf1-scrolls", "documentId": "ceByufFhsOvdeLgy", "flags": {}}, {"type": 2, "weight": 1, "range": [223, 223], "drawn": false, "text": "Scroll of Possession", "img": "systems/pf1/icons/items/inventory/scroll-magic.jpg", "documentCollection": "world.pf1-scrolls", "documentId": "chRqVO9cHqPIUeRs", "flags": {}}, {"type": 2, "weight": 1, "range": [224, 224], "drawn": false, "text": "Scroll of Compel Tongue, Mass", "img": "systems/pf1/icons/items/inventory/scroll-magic.jpg", "documentCollection": "world.pf1-scrolls", "documentId": "dMl7xBGuB0YgFrq0", "flags": {}}, {"type": 2, "weight": 1, "range": [225, 225], "drawn": false, "text": "Scroll of Condensed Ether", "img": "systems/pf1/icons/items/inventory/scroll-magic.jpg", "documentCollection": "world.pf1-scrolls", "documentId": "dXbpWr62ACeX8kn2", "flags": {}}, {"type": 2, "weight": 1, "range": [226, 226], "drawn": false, "text": "Scroll of Frozen Note", "img": "systems/pf1/icons/items/inventory/scroll-magic.jpg", "documentCollection": "world.pf1-scrolls", "documentId": "dgzgBkHwiw4Dssi3", "flags": {}}, {"type": 2, "weight": 1, "range": [227, 227], "drawn": false, "text": "Scroll of Master's Mutation", "img": "systems/pf1/icons/items/inventory/scroll-magic.jpg", "documentCollection": "world.pf1-scrolls", "documentId": "e0Wl1HFF8Q8CDv5k", "flags": {}}, {"type": 2, "weight": 1, "range": [228, 228], "drawn": false, "text": "Scroll of Spell Resistance", "img": "systems/pf1/icons/items/inventory/scroll-magic.jpg", "documentCollection": "world.pf1-scrolls", "documentId": "eJyDvNmGr7D2oZzy", "flags": {}}, {"type": 2, "weight": 1, "range": [229, 229], "drawn": false, "text": "Scroll of Village Veil", "img": "systems/pf1/icons/items/inventory/scroll-magic.jpg", "documentCollection": "world.pf1-scrolls", "documentId": "eqeMldZs6ZE1aMnE", "flags": {}}, {"type": 2, "weight": 1, "range": [230, 230], "drawn": false, "text": "Scroll of Vampiric Shadow Shield", "img": "systems/pf1/icons/items/inventory/scroll-magic.jpg", "documentCollection": "world.pf1-scrolls", "documentId": "f2zhV6fP6YXiLJXq", "flags": {}}, {"type": 2, "weight": 1, "range": [231, 231], "drawn": false, "text": "Scroll of Decollate", "img": "systems/pf1/icons/items/inventory/scroll-magic.jpg", "documentCollection": "world.pf1-scrolls", "documentId": "fcMTBtXCy6t1g0LI", "flags": {}}, {"type": 2, "weight": 1, "range": [232, 232], "drawn": false, "text": "Scroll of Sonic Thrust", "img": "systems/pf1/icons/items/inventory/scroll-magic.jpg", "documentCollection": "world.pf1-scrolls", "documentId": "g46ZHh24g7j8kUNV", "flags": {}}, {"type": 2, "weight": 1, "range": [233, 233], "drawn": false, "text": "Scroll of False Vision", "img": "systems/pf1/icons/items/inventory/scroll-magic.jpg", "documentCollection": "world.pf1-scrolls", "documentId": "gAGhxUBjDhLtsYLT", "flags": {}}, {"type": 2, "weight": 1, "range": [234, 234], "drawn": false, "text": "Scroll of Feeblemind", "img": "systems/pf1/icons/items/inventory/scroll-magic.jpg", "documentCollection": "world.pf1-scrolls", "documentId": "gArGRG4d3ZhRIZ0r", "flags": {}}, {"type": 2, "weight": 1, "range": [235, 235], "drawn": false, "text": "Scroll of Transmute Mud to Rock", "img": "systems/pf1/icons/items/inventory/scroll-magic.jpg", "documentCollection": "world.pf1-scrolls", "documentId": "ggl1aEwDZAapnL0G", "flags": {}}, {"type": 2, "weight": 1, "range": [236, 236], "drawn": false, "text": "Scroll of Dispel Chaos", "img": "systems/pf1/icons/items/inventory/scroll-magic.jpg", "documentCollection": "world.pf1-scrolls", "documentId": "glKbpZwSMKN6NdkR", "flags": {}}, {"type": 2, "weight": 1, "range": [237, 237], "drawn": false, "text": "Scroll of Wall of Force", "img": "systems/pf1/icons/items/inventory/scroll-magic.jpg", "documentCollection": "world.pf1-scrolls", "documentId": "hB4LBO2WG8km9X8q", "flags": {}}, {"type": 2, "weight": 1, "range": [238, 238], "drawn": false, "text": "Scroll of Stoneskin, Communal", "img": "systems/pf1/icons/items/inventory/scroll-magic.jpg", "documentCollection": "world.pf1-scrolls", "documentId": "hNL9abOOWGb6EHoJ", "flags": {}}, {"type": 2, "weight": 1, "range": [239, 239], "drawn": false, "text": "Scroll of Devil Snare", "img": "systems/pf1/icons/items/inventory/scroll-magic.jpg", "documentCollection": "world.pf1-scrolls", "documentId": "hcQWrMj7enrvWUa7", "flags": {}}, {"type": 2, "weight": 1, "range": [240, 240], "drawn": false, "text": "Scroll of Summon Nature's Ally V", "img": "systems/pf1/icons/items/inventory/scroll-magic.jpg", "documentCollection": "world.pf1-scrolls", "documentId": "hiZQvyDsYbQ3fV7v", "flags": {}}, {"type": 2, "weight": 1, "range": [241, 241], "drawn": false, "text": "Scroll of Unhallow", "img": "systems/pf1/icons/items/inventory/scroll-magic.jpg", "documentCollection": "world.pf1-scrolls", "documentId": "i4lXjBFDs8a90Ptu", "flags": {}}, {"type": 2, "weight": 1, "range": [242, 242], "drawn": false, "text": "Scroll of Planar Binding, Lesser", "img": "systems/pf1/icons/items/inventory/scroll-magic.jpg", "documentCollection": "world.pf1-scrolls", "documentId": "iNj3CduobgjR8UpP", "flags": {}}, {"type": 2, "weight": 1, "range": [243, 243], "drawn": false, "text": "Scroll of Control Winds", "img": "systems/pf1/icons/items/inventory/scroll-magic.jpg", "documentCollection": "world.pf1-scrolls", "documentId": "itxnlgXRcCuXhJkk", "flags": {}}, {"type": 2, "weight": 1, "range": [244, 244], "drawn": false, "text": "Scroll of Ectoplasmic Hand", "img": "systems/pf1/icons/items/inventory/scroll-magic.jpg", "documentCollection": "world.pf1-scrolls", "documentId": "j1ZNWswu3X73cEpC", "flags": {}}, {"type": 2, "weight": 1, "range": [245, 245], "drawn": false, "text": "Scroll of Unshakable Zeal", "img": "systems/pf1/icons/items/inventory/scroll-magic.jpg", "documentCollection": "world.pf1-scrolls", "documentId": "j4eB9YMGRcany3tB", "flags": {}}, {"type": 2, "weight": 1, "range": [246, 246], "drawn": false, "text": "Scroll of Burst of Glory", "img": "systems/pf1/icons/items/inventory/scroll-magic.jpg", "documentCollection": "world.pf1-scrolls", "documentId": "jAJGWwbWzK9HaUQ5", "flags": {}}, {"type": 2, "weight": 1, "range": [247, 247], "drawn": false, "text": "Scroll of Insect Plague", "img": "systems/pf1/icons/items/inventory/scroll-magic.jpg", "documentCollection": "world.pf1-scrolls", "documentId": "jGxpHPyE5awzZBZX", "flags": {}}, {"type": 2, "weight": 1, "range": [248, 248], "drawn": false, "text": "Scroll of Inflict Light Wounds, Mass", "img": "systems/pf1/icons/items/inventory/scroll-magic.jpg", "documentCollection": "world.pf1-scrolls", "documentId": "jXyzgFI20PBZ6Cya", "flags": {}}, {"type": 2, "weight": 1, "range": [249, 249], "drawn": false, "text": "Scroll of Fickle Winds", "img": "systems/pf1/icons/items/inventory/scroll-magic.jpg", "documentCollection": "world.pf1-scrolls", "documentId": "jp9SnOGy6Zvn0oxo", "flags": {}}, {"type": 2, "weight": 1, "range": [250, 250], "drawn": false, "text": "Scroll of Illusory Hoard", "img": "systems/pf1/icons/items/inventory/scroll-magic.jpg", "documentCollection": "world.pf1-scrolls", "documentId": "jqwYbnE2PbB2JTxn", "flags": {}}, {"type": 2, "weight": 1, "range": [251, 251], "drawn": false, "text": "Scroll of Passing Fancy, Mass", "img": "systems/pf1/icons/items/inventory/scroll-magic.jpg", "documentCollection": "world.pf1-scrolls", "documentId": "jrBlI8KLj9vALdjh", "flags": {}}, {"type": 2, "weight": 1, "range": [252, 252], "drawn": false, "text": "Scroll of Roaming Pit", "img": "systems/pf1/icons/items/inventory/scroll-magic.jpg", "documentCollection": "world.pf1-scrolls", "documentId": "jxIaUidVgD6az2Qd", "flags": {}}, {"type": 2, "weight": 1, "range": [253, 253], "drawn": false, "text": "Scroll of Object Possession", "img": "systems/pf1/icons/items/inventory/scroll-magic.jpg", "documentCollection": "world.pf1-scrolls", "documentId": "kQkraO69AYIY1AZy", "flags": {}}, {"type": 2, "weight": 1, "range": [254, 254], "drawn": false, "text": "Scroll of Commune with Nature", "img": "systems/pf1/icons/items/inventory/scroll-magic.jpg", "documentCollection": "world.pf1-scrolls", "documentId": "kQxzbVMlSLSX5HfE", "flags": {}}, {"type": 2, "weight": 1, "range": [255, 255], "drawn": false, "text": "Scroll of Death Pact", "img": "systems/pf1/icons/items/inventory/scroll-magic.jpg", "documentCollection": "world.pf1-scrolls", "documentId": "kdYuSTAE35eGD0Xr", "flags": {}}, {"type": 2, "weight": 1, "range": [256, 256], "drawn": false, "text": "Scroll of Constricting Coils", "img": "systems/pf1/icons/items/inventory/scroll-magic.jpg", "documentCollection": "world.pf1-scrolls", "documentId": "kmDQuqr6YZxaNe20", "flags": {}}, {"type": 2, "weight": 1, "range": [257, 257], "drawn": false, "text": "Scroll of Shroud of Darkness", "img": "systems/pf1/icons/items/inventory/scroll-magic.jpg", "documentCollection": "world.pf1-scrolls", "documentId": "kmLjqmmwnKCMn2fm", "flags": {}}, {"type": 2, "weight": 1, "range": [258, 258], "drawn": false, "text": "Scroll of Smite Abomination", "img": "systems/pf1/icons/items/inventory/scroll-magic.jpg", "documentCollection": "world.pf1-scrolls", "documentId": "ktXUgq9AMrh2uUlX", "flags": {}}, {"type": 2, "weight": 1, "range": [259, 259], "drawn": false, "text": "Scroll of Blood Ties", "img": "systems/pf1/icons/items/inventory/scroll-magic.jpg", "documentCollection": "world.pf1-scrolls", "documentId": "kwvQ64uelojuqOtk", "flags": {}}, {"type": 2, "weight": 1, "range": [260, 260], "drawn": false, "text": "Scroll of Plague Carrier", "img": "systems/pf1/icons/items/inventory/scroll-magic.jpg", "documentCollection": "world.pf1-scrolls", "documentId": "lIxbcZBlSqSQVpIS", "flags": {}}, {"type": 2, "weight": 1, "range": [261, 261], "drawn": false, "text": "Scroll of Gravity Sphere", "img": "systems/pf1/icons/items/inventory/scroll-magic.jpg", "documentCollection": "world.pf1-scrolls", "documentId": "lWKMDOJvS3EzWvWY", "flags": {}}, {"type": 2, "weight": 1, "range": [262, 262], "drawn": false, "text": "Scroll of Corrosive Consumption", "img": "systems/pf1/icons/items/inventory/scroll-magic.jpg", "documentCollection": "world.pf1-scrolls", "documentId": "lX9uI89ZpshNqwjI", "flags": {}}, {"type": 2, "weight": 1, "range": [263, 263], "drawn": false, "text": "Scroll of Snake Staff", "img": "systems/pf1/icons/items/inventory/scroll-magic.jpg", "documentCollection": "world.pf1-scrolls", "documentId": "lb2x22bj1vh4hkhZ", "flags": {}}, {"type": 2, "weight": 1, "range": [264, 264], "drawn": false, "text": "Scroll of Wall of Stone", "img": "systems/pf1/icons/items/inventory/scroll-magic.jpg", "documentCollection": "world.pf1-scrolls", "documentId": "liEVqwlaqGUfyh4j", "flags": {}}, {"type": 2, "weight": 1, "range": [265, 265], "drawn": false, "text": "Scroll of Sequester Thoughts", "img": "systems/pf1/icons/items/inventory/scroll-magic.jpg", "documentCollection": "world.pf1-scrolls", "documentId": "lkfZSLSk5iaij2eW", "flags": {}}, {"type": 2, "weight": 1, "range": [266, 266], "drawn": false, "text": "Scroll of Unbreakable Construct", "img": "systems/pf1/icons/items/inventory/scroll-magic.jpg", "documentCollection": "world.pf1-scrolls", "documentId": "m6yapA8t0mTqrVqh", "flags": {}}, {"type": 2, "weight": 1, "range": [267, 267], "drawn": false, "text": "Scroll of Dispel Balance", "img": "systems/pf1/icons/items/inventory/scroll-magic.jpg", "documentCollection": "world.pf1-scrolls", "documentId": "mCqGTkZ3XfsVg4Sv", "flags": {}}, {"type": 2, "weight": 1, "range": [268, 268], "drawn": false, "text": "Scroll of Icy Prison", "img": "systems/pf1/icons/items/inventory/scroll-magic.jpg", "documentCollection": "world.pf1-scrolls", "documentId": "mOnXO1lcy3bkigpQ", "flags": {}}, {"type": 2, "weight": 1, "range": [269, 269], "drawn": false, "text": "Scroll of Planar Aegis", "img": "systems/pf1/icons/items/inventory/scroll-magic.jpg", "documentCollection": "world.pf1-scrolls", "documentId": "mPI5oLCywRTjEKy1", "flags": {}}, {"type": 2, "weight": 1, "range": [270, 270], "drawn": false, "text": "Scroll of Planeslayer's Call", "img": "systems/pf1/icons/items/inventory/scroll-magic.jpg", "documentCollection": "world.pf1-scrolls", "documentId": "mZekzBiESlBkT1gD", "flags": {}}, {"type": 2, "weight": 1, "range": [271, 271], "drawn": false, "text": "Scroll of Foe to Friend", "img": "systems/pf1/icons/items/inventory/scroll-magic.jpg", "documentCollection": "world.pf1-scrolls", "documentId": "mgaRuByNtCITClU5", "flags": {}}, {"type": 2, "weight": 1, "range": [272, 272], "drawn": false, "text": "Scroll of Mantle of the Magic Warriors", "img": "systems/pf1/icons/items/inventory/scroll-magic.jpg", "documentCollection": "world.pf1-scrolls", "documentId": "mifUuIqWBAVPulpq", "flags": {}}, {"type": 2, "weight": 1, "range": [273, 273], "drawn": false, "text": "Scroll of Thought Shield IV", "img": "systems/pf1/icons/items/inventory/scroll-magic.jpg", "documentCollection": "world.pf1-scrolls", "documentId": "n8nIbvIYKAvbORGC", "flags": {}}, {"type": 2, "weight": 1, "range": [274, 274], "drawn": false, "text": "Scroll of Angelic Aspect", "img": "systems/pf1/icons/items/inventory/scroll-magic.jpg", "documentCollection": "world.pf1-scrolls", "documentId": "nA3aCsFxaqX0kKQa", "flags": {}}, {"type": 2, "weight": 1, "range": [275, 275], "drawn": false, "text": "Scroll of Smug Narcissism", "img": "systems/pf1/icons/items/inventory/scroll-magic.jpg", "documentCollection": "world.pf1-scrolls", "documentId": "nApxvamYEAyWvHzi", "flags": {}}, {"type": 2, "weight": 1, "range": [276, 276], "drawn": false, "text": "Scroll of Id Insinuation IV", "img": "systems/pf1/icons/items/inventory/scroll-magic.jpg", "documentCollection": "world.pf1-scrolls", "documentId": "nFJla4JXUrfYEoOO", "flags": {}}, {"type": 2, "weight": 1, "range": [277, 277], "drawn": false, "text": "Scroll of Blessing of the Salamander", "img": "systems/pf1/icons/items/inventory/scroll-magic.jpg", "documentCollection": "world.pf1-scrolls", "documentId": "nG3gU5vMrRUz0rAD", "flags": {}}, {"type": 2, "weight": 1, "range": [278, 278], "drawn": false, "text": "Scroll of Blood Boil", "img": "systems/pf1/icons/items/inventory/scroll-magic.jpg", "documentCollection": "world.pf1-scrolls", "documentId": "nRzM8zWVX9ZFJtuC", "flags": {}}, {"type": 2, "weight": 1, "range": [279, 279], "drawn": false, "text": "Scroll of Cleansing Fire", "img": "systems/pf1/icons/items/inventory/scroll-magic.jpg", "documentCollection": "world.pf1-scrolls", "documentId": "nV2Hv61F84BTAj8B", "flags": {}}, {"type": 2, "weight": 1, "range": [280, 280], "drawn": false, "text": "Scroll of Profane Nimbus", "img": "systems/pf1/icons/items/inventory/scroll-magic.jpg", "documentCollection": "world.pf1-scrolls", "documentId": "nWmhRw1UDs3kx4VB", "flags": {}}, {"type": 2, "weight": 1, "range": [281, 281], "drawn": false, "text": "Scroll of Sawtooth Terrain", "img": "systems/pf1/icons/items/inventory/scroll-magic.jpg", "documentCollection": "world.pf1-scrolls", "documentId": "nXSJ0L6wKQRLcdS1", "flags": {}}, {"type": 2, "weight": 1, "range": [282, 282], "drawn": false, "text": "Scroll of Wall of Thorns", "img": "systems/pf1/icons/items/inventory/scroll-magic.jpg", "documentCollection": "world.pf1-scrolls", "documentId": "oEZTTolFKfIQX756", "flags": {}}, {"type": 2, "weight": 1, "range": [283, 283], "drawn": false, "text": "Scroll of Guardian Monument, Greater", "img": "systems/pf1/icons/items/inventory/scroll-magic.jpg", "documentCollection": "world.pf1-scrolls", "documentId": "oF44iKmudRLnShll", "flags": {}}, {"type": 2, "weight": 1, "range": [284, 284], "drawn": false, "text": "Scroll of Gift of the Deep", "img": "systems/pf1/icons/items/inventory/scroll-magic.jpg", "documentCollection": "world.pf1-scrolls", "documentId": "oHzdBg2BXK3c81Am", "flags": {}}, {"type": 2, "weight": 1, "range": [285, 285], "drawn": false, "text": "Scroll of Summon Monster V", "img": "systems/pf1/icons/items/inventory/scroll-magic.jpg", "documentCollection": "world.pf1-scrolls", "documentId": "oTF6wvozO1tMezGS", "flags": {}}, {"type": 2, "weight": 1, "range": [286, 286], "drawn": false, "text": "Scroll of Rejuvenate Eidolon, Greater", "img": "systems/pf1/icons/items/inventory/scroll-magic.jpg", "documentCollection": "world.pf1-scrolls", "documentId": "oXisIqarVfaLUApd", "flags": {}}, {"type": 2, "weight": 1, "range": [287, 287], "drawn": false, "text": "Scroll of Pain Strike, Mass", "img": "systems/pf1/icons/items/inventory/scroll-magic.jpg", "documentCollection": "world.pf1-scrolls", "documentId": "oaqU2hoPL0GanOsQ", "flags": {}}, {"type": 2, "weight": 1, "range": [288, 288], "drawn": false, "text": "Scroll of Summon Ceustodaemon", "img": "systems/pf1/icons/items/inventory/scroll-magic.jpg", "documentCollection": "world.pf1-scrolls", "documentId": "oo6qgQktqaDSyXrj", "flags": {}}, {"type": 2, "weight": 1, "range": [289, 289], "drawn": false, "text": "Scroll of Major Phantom Object", "img": "systems/pf1/icons/items/inventory/scroll-magic.jpg", "documentCollection": "world.pf1-scrolls", "documentId": "opu2ZM2BcP1qHRVm", "flags": {}}, {"type": 2, "weight": 1, "range": [290, 290], "drawn": false, "text": "Scroll of Bard's Escape", "img": "systems/pf1/icons/items/inventory/scroll-magic.jpg", "documentCollection": "world.pf1-scrolls", "documentId": "orNBou2oJm2WC2qG", "flags": {}}, {"type": 2, "weight": 1, "range": [291, 291], "drawn": false, "text": "Scroll of Sphere of Warding", "img": "systems/pf1/icons/items/inventory/scroll-magic.jpg", "documentCollection": "world.pf1-scrolls", "documentId": "p8yalNsYTTl1Gxuz", "flags": {}}, {"type": 2, "weight": 1, "range": [292, 292], "drawn": false, "text": "Scroll of Replay Tracks", "img": "systems/pf1/icons/items/inventory/scroll-magic.jpg", "documentCollection": "world.pf1-scrolls", "documentId": "pPYARNwQs5YHpHNB", "flags": {}}, {"type": 2, "weight": 1, "range": [293, 293], "drawn": false, "text": "Scroll of Planetary Adaptation", "img": "systems/pf1/icons/items/inventory/scroll-magic.jpg", "documentCollection": "world.pf1-scrolls", "documentId": "pcX8Nu9hd1Ikr7I1", "flags": {}}, {"type": 2, "weight": 1, "range": [294, 294], "drawn": false, "text": "Scroll of Sessile Spirit", "img": "systems/pf1/icons/items/inventory/scroll-magic.jpg", "documentCollection": "world.pf1-scrolls", "documentId": "pi5VxmlXJDSlAnqH", "flags": {}}, {"type": 2, "weight": 1, "range": [295, 295], "drawn": false, "text": "Scroll of Awaken", "img": "systems/pf1/icons/items/inventory/scroll-magic.jpg", "documentCollection": "world.pf1-scrolls", "documentId": "pjTVuitjxWfpvIpk", "flags": {}}, {"type": 2, "weight": 1, "range": [296, 296], "drawn": false, "text": "Scroll of Invoke Primal Power", "img": "systems/pf1/icons/items/inventory/scroll-magic.jpg", "documentCollection": "world.pf1-scrolls", "documentId": "qgBBveo4qIjaKDqJ", "flags": {}}, {"type": 2, "weight": 1, "range": [297, 297], "drawn": false, "text": "Scroll of Shapechanger's Gift", "img": "systems/pf1/icons/items/inventory/scroll-magic.jpg", "documentCollection": "world.pf1-scrolls", "documentId": "qvbfY6Yn5uuvLaAl", "flags": {}}, {"type": 2, "weight": 1, "range": [298, 298], "drawn": false, "text": "Scroll of Spellsteal", "img": "systems/pf1/icons/items/inventory/scroll-magic.jpg", "documentCollection": "world.pf1-scrolls", "documentId": "r5kinkykHVeurVoX", "flags": {}}, {"type": 2, "weight": 1, "range": [299, 299], "drawn": false, "text": "Scroll of Divine Pursuit", "img": "systems/pf1/icons/items/inventory/scroll-magic.jpg", "documentCollection": "world.pf1-scrolls", "documentId": "rG5VkVjz57TmkvOO", "flags": {}}, {"type": 2, "weight": 1, "range": [300, 300], "drawn": false, "text": "Scroll of Waves of Fatigue", "img": "systems/pf1/icons/items/inventory/scroll-magic.jpg", "documentCollection": "world.pf1-scrolls", "documentId": "rZ8g5e78Lrpm5hMB", "flags": {}}, {"type": 2, "weight": 1, "range": [301, 301], "drawn": false, "text": "Scroll of Covetous Aura", "img": "systems/pf1/icons/items/inventory/scroll-magic.jpg", "documentCollection": "world.pf1-scrolls", "documentId": "rhOz3dWL4h0qnmoC", "flags": {}}, {"type": 2, "weight": 1, "range": [302, 302], "drawn": false, "text": "Scroll of Psychic Crush I", "img": "systems/pf1/icons/items/inventory/scroll-magic.jpg", "documentCollection": "world.pf1-scrolls", "documentId": "rtJMxxRz9CJOSKtD", "flags": {}}, {"type": 2, "weight": 1, "range": [303, 303], "drawn": false, "text": "Scroll of Flash Forward", "img": "systems/pf1/icons/items/inventory/scroll-magic.jpg", "documentCollection": "world.pf1-scrolls", "documentId": "s5nTtoPEXLpenp3v", "flags": {}}, {"type": 2, "weight": 1, "range": [304, 304], "drawn": false, "text": "Scroll of Spawn Ward", "img": "systems/pf1/icons/items/inventory/scroll-magic.jpg", "documentCollection": "world.pf1-scrolls", "documentId": "s8T6cT9WULJNnLXx", "flags": {}}, {"type": 2, "weight": 1, "range": [305, 305], "drawn": false, "text": "Scroll of Dominate Person", "img": "systems/pf1/icons/items/inventory/scroll-magic.jpg", "documentCollection": "world.pf1-scrolls", "documentId": "sA85jUjAqHTLBLfC", "flags": {}}, {"type": 2, "weight": 1, "range": [306, 306], "drawn": false, "text": "Scroll of Lightning Arc", "img": "systems/pf1/icons/items/inventory/scroll-magic.jpg", "documentCollection": "world.pf1-scrolls", "documentId": "sJ9lkVPP9BVGICj6", "flags": {}}, {"type": 2, "weight": 1, "range": [307, 307], "drawn": false, "text": "Scroll of Possess Object", "img": "systems/pf1/icons/items/inventory/scroll-magic.jpg", "documentCollection": "world.pf1-scrolls", "documentId": "sXcQbYo0HaZOuO9W", "flags": {}}, {"type": 2, "weight": 1, "range": [308, 308], "drawn": false, "text": "Scroll of Mirage Arcana", "img": "systems/pf1/icons/items/inventory/scroll-magic.jpg", "documentCollection": "world.pf1-scrolls", "documentId": "scuVFqEEW3Xjx7EL", "flags": {}}, {"type": 2, "weight": 1, "range": [309, 309], "drawn": false, "text": "Scroll of Ghostbane Dirge, Mass", "img": "systems/pf1/icons/items/inventory/scroll-magic.jpg", "documentCollection": "world.pf1-scrolls", "documentId": "sf4ZZPAS5PX1v6D2", "flags": {}}, {"type": 2, "weight": 1, "range": [310, 310], "drawn": false, "text": "Scroll of Lend Path", "img": "systems/pf1/icons/items/inventory/scroll-magic.jpg", "documentCollection": "world.pf1-scrolls", "documentId": "swpslfs4mM0SGXKs", "flags": {}}, {"type": 2, "weight": 1, "range": [311, 311], "drawn": false, "text": "Scroll of Polymorph", "img": "systems/pf1/icons/items/inventory/scroll-magic.jpg", "documentCollection": "world.pf1-scrolls", "documentId": "t1jnUEuFMgPdVZRG", "flags": {}}, {"type": 2, "weight": 1, "range": [312, 312], "drawn": false, "text": "Scroll of Symbol of Sleep", "img": "systems/pf1/icons/items/inventory/scroll-magic.jpg", "documentCollection": "world.pf1-scrolls", "documentId": "t9mXTCdg0xBEQe9Y", "flags": {}}, {"type": 2, "weight": 1, "range": [313, 313], "drawn": false, "text": "Scroll of Wreath of Blades", "img": "systems/pf1/icons/items/inventory/scroll-magic.jpg", "documentCollection": "world.pf1-scrolls", "documentId": "tO9CxOnTRVBU2NNM", "flags": {}}, {"type": 2, "weight": 1, "range": [314, 314], "drawn": false, "text": "Scroll of Geyser", "img": "systems/pf1/icons/items/inventory/scroll-magic.jpg", "documentCollection": "world.pf1-scrolls", "documentId": "ti2Ed85uO3b2A9xq", "flags": {}}, {"type": 2, "weight": 1, "range": [315, 315], "drawn": false, "text": "Scroll of Summon Infernal Host", "img": "systems/pf1/icons/items/inventory/scroll-magic.jpg", "documentCollection": "world.pf1-scrolls", "documentId": "u1ezJPu9jo8QRCum", "flags": {}}, {"type": 2, "weight": 1, "range": [316, 316], "drawn": false, "text": "Scroll of Soulswitch", "img": "systems/pf1/icons/items/inventory/scroll-magic.jpg", "documentCollection": "world.pf1-scrolls", "documentId": "u3v2vpUZU9wJjrXk", "flags": {}}, {"type": 2, "weight": 1, "range": [317, 317], "drawn": false, "text": "Scroll of Empathy Conduit", "img": "systems/pf1/icons/items/inventory/scroll-magic.jpg", "documentCollection": "world.pf1-scrolls", "documentId": "u4P5AYYnXxrKLQzT", "flags": {}}, {"type": 2, "weight": 1, "range": [318, 318], "drawn": false, "text": "Scroll of Unholy Ice", "img": "systems/pf1/icons/items/inventory/scroll-magic.jpg", "documentCollection": "world.pf1-scrolls", "documentId": "uJlpCg4Elet37tyP", "flags": {}}, {"type": 2, "weight": 1, "range": [319, 319], "drawn": false, "text": "Scroll of Dream", "img": "systems/pf1/icons/items/inventory/scroll-magic.jpg", "documentCollection": "world.pf1-scrolls", "documentId": "uSUq1Gy9r7sV7rXj", "flags": {}}, {"type": 2, "weight": 1, "range": [320, 320], "drawn": false, "text": "Scroll of Apparent Master", "img": "systems/pf1/icons/items/inventory/scroll-magic.jpg", "documentCollection": "world.pf1-scrolls", "documentId": "v15KoBpeGSka2Mdt", "flags": {}}, {"type": 2, "weight": 1, "range": [321, 321], "drawn": false, "text": "Scroll of Foster Hatred", "img": "systems/pf1/icons/items/inventory/scroll-magic.jpg", "documentCollection": "world.pf1-scrolls", "documentId": "vDEfCy9HjJ9YVjmt", "flags": {}}, {"type": 2, "weight": 1, "range": [322, 322], "drawn": false, "text": "Scroll of Swallow Poison", "img": "systems/pf1/icons/items/inventory/scroll-magic.jpg", "documentCollection": "world.pf1-scrolls", "documentId": "vvVr65jndaF1lKm5", "flags": {}}, {"type": 2, "weight": 1, "range": [323, 323], "drawn": false, "text": "Scroll of Jungle Mind", "img": "systems/pf1/icons/items/inventory/scroll-magic.jpg", "documentCollection": "world.pf1-scrolls", "documentId": "vvsmygZCdIBUqoR9", "flags": {}}, {"type": 2, "weight": 1, "range": [324, 324], "drawn": false, "text": "Scroll of Awaken the Devoured", "img": "systems/pf1/icons/items/inventory/scroll-magic.jpg", "documentCollection": "world.pf1-scrolls", "documentId": "vxoBEGETiBk88HmV", "flags": {}}, {"type": 2, "weight": 1, "range": [325, 325], "drawn": false, "text": "Scroll of Banishing Blade", "img": "systems/pf1/icons/items/inventory/scroll-magic.jpg", "documentCollection": "world.pf1-scrolls", "documentId": "w5JJqw857WGeM7z2", "flags": {}}, {"type": 2, "weight": 1, "range": [326, 326], "drawn": false, "text": "Scroll of Lighten Object, Mass", "img": "systems/pf1/icons/items/inventory/scroll-magic.jpg", "documentCollection": "world.pf1-scrolls", "documentId": "wDyPF8YJVGfGF4DB", "flags": {}}, {"type": 2, "weight": 1, "range": [327, 327], "drawn": false, "text": "Scroll of Siege Scatter", "img": "systems/pf1/icons/items/inventory/scroll-magic.jpg", "documentCollection": "world.pf1-scrolls", "documentId": "wEujZhSZyBCEaoEb", "flags": {}}, {"type": 2, "weight": 1, "range": [328, 328], "drawn": false, "text": "Scroll of Tower of Iron Will I", "img": "systems/pf1/icons/items/inventory/scroll-magic.jpg", "documentCollection": "world.pf1-scrolls", "documentId": "wRDyQrTYqDf2zkXf", "flags": {}}, {"type": 2, "weight": 1, "range": [329, 329], "drawn": false, "text": "Scroll of Sealed Sending", "img": "systems/pf1/icons/items/inventory/scroll-magic.jpg", "documentCollection": "world.pf1-scrolls", "documentId": "wSX3iVlSXAFKeZZH", "flags": {}}, {"type": 2, "weight": 1, "range": [330, 330], "drawn": false, "text": "Scroll of Charnel House", "img": "systems/pf1/icons/items/inventory/scroll-magic.jpg", "documentCollection": "world.pf1-scrolls", "documentId": "wStzlXzYGVnqEZDV", "flags": {}}, {"type": 2, "weight": 1, "range": [331, 331], "drawn": false, "text": "Scroll of Synaptic Pulse, Greater", "img": "systems/pf1/icons/items/inventory/scroll-magic.jpg", "documentCollection": "world.pf1-scrolls", "documentId": "wYmRQxBllFDE9xWY", "flags": {}}, {"type": 2, "weight": 1, "range": [332, 332], "drawn": false, "text": "Scroll of Scintillating Wall", "img": "systems/pf1/icons/items/inventory/scroll-magic.jpg", "documentCollection": "world.pf1-scrolls", "documentId": "wv9nq9bcKLj8nDSo", "flags": {}}, {"type": 2, "weight": 1, "range": [333, 333], "drawn": false, "text": "Scroll of Life Bubble", "img": "systems/pf1/icons/items/inventory/scroll-magic.jpg", "documentCollection": "world.pf1-scrolls", "documentId": "xCAl9IxWMp6cQDjL", "flags": {}}, {"type": 2, "weight": 1, "range": [334, 334], "drawn": false, "text": "Scroll of Curse of Disgust", "img": "systems/pf1/icons/items/inventory/scroll-magic.jpg", "documentCollection": "world.pf1-scrolls", "documentId": "xUmmBUNFarEGdmOG", "flags": {}}, {"type": 2, "weight": 1, "range": [335, 335], "drawn": false, "text": "Scroll of Planar Adaptation", "img": "systems/pf1/icons/items/inventory/scroll-magic.jpg", "documentCollection": "world.pf1-scrolls", "documentId": "xZlWSt4kTUFYgQ57", "flags": {}}, {"type": 2, "weight": 1, "range": [336, 336], "drawn": false, "text": "Scroll of Wall of Clockwork", "img": "systems/pf1/icons/items/inventory/scroll-magic.jpg", "documentCollection": "world.pf1-scrolls", "documentId": "xbk2CQMA1ZFMkqE6", "flags": {}}, {"type": 2, "weight": 1, "range": [337, 337], "drawn": false, "text": "Scroll of Resurgent Transformation", "img": "systems/pf1/icons/items/inventory/scroll-magic.jpg", "documentCollection": "world.pf1-scrolls", "documentId": "xlkASCCsgtLJ8AOW", "flags": {}}, {"type": 2, "weight": 1, "range": [338, 338], "drawn": false, "text": "Scroll of Mind Thrust V", "img": "systems/pf1/icons/items/inventory/scroll-magic.jpg", "documentCollection": "world.pf1-scrolls", "documentId": "xzIXg7akFX1jN34Q", "flags": {}}, {"type": 2, "weight": 1, "range": [339, 339], "drawn": false, "text": "Scroll of Half-Blood Extraction", "img": "systems/pf1/icons/items/inventory/scroll-magic.jpg", "documentCollection": "world.pf1-scrolls", "documentId": "yBwWSKAl1Jzw4fn0", "flags": {}}, {"type": 2, "weight": 1, "range": [340, 340], "drawn": false, "text": "Scroll of Reprobation", "img": "systems/pf1/icons/items/inventory/scroll-magic.jpg", "documentCollection": "world.pf1-scrolls", "documentId": "yG9XmzOeALNqeVDa", "flags": {}}, {"type": 2, "weight": 1, "range": [341, 341], "drawn": false, "text": "Scroll of Scripted Hallucination", "img": "systems/pf1/icons/items/inventory/scroll-magic.jpg", "documentCollection": "world.pf1-scrolls", "documentId": "yZVsn1V9K6G8YKTI", "flags": {}}, {"type": 2, "weight": 1, "range": [342, 342], "drawn": false, "text": "Scroll of Plant Shape I", "img": "systems/pf1/icons/items/inventory/scroll-magic.jpg", "documentCollection": "world.pf1-scrolls", "documentId": "ysn5IyGIYlgooFSm", "flags": {}}, {"type": 2, "weight": 1, "range": [343, 343], "drawn": false, "text": "Scroll of Ego Whip III", "img": "systems/pf1/icons/items/inventory/scroll-magic.jpg", "documentCollection": "world.pf1-scrolls", "documentId": "yvX321ZLrFpWFumu", "flags": {}}, {"type": 2, "weight": 1, "range": [344, 344], "drawn": false, "text": "Scroll of Entice Fey, Lesser", "img": "systems/pf1/icons/items/inventory/scroll-magic.jpg", "documentCollection": "world.pf1-scrolls", "documentId": "yvkFMJJ2o14ZmvRW", "flags": {}}, {"type": 2, "weight": 1, "range": [345, 345], "drawn": false, "text": "Scroll of Hungry Pit", "img": "systems/pf1/icons/items/inventory/scroll-magic.jpg", "documentCollection": "world.pf1-scrolls", "documentId": "ywcklkfxiu60fKBI", "flags": {}}, {"type": 2, "weight": 1, "range": [346, 346], "drawn": false, "text": "Scroll of Rend Body I", "img": "systems/pf1/icons/items/inventory/scroll-magic.jpg", "documentCollection": "world.pf1-scrolls", "documentId": "zHxP0jwKLdA1Twcg", "flags": {}}, {"type": 2, "weight": 1, "range": [347, 347], "drawn": false, "text": "Scroll of Treasure Stitching", "img": "systems/pf1/icons/items/inventory/scroll-magic.jpg", "documentCollection": "world.pf1-scrolls", "documentId": "zJPdvogijMpVB2Nr", "flags": {}}, {"type": 2, "weight": 1, "range": [348, 348], "drawn": false, "text": "Scroll of Commune with Texts", "img": "systems/pf1/icons/items/inventory/scroll-magic.jpg", "documentCollection": "world.pf1-scrolls", "documentId": "zU7STYTgJ4BMhsn5", "flags": {}}, {"type": 2, "weight": 1, "range": [349, 349], "drawn": false, "text": "Scroll of Talisman of Reprieve", "img": "systems/pf1/icons/items/inventory/scroll-magic.jpg", "documentCollection": "world.pf1-scrolls", "documentId": "zXmUtaTSKH4n7TbI", "flags": {}}, {"type": 2, "weight": 1, "range": [350, 350], "drawn": false, "text": "Scroll of Imbue Hex", "img": "systems/pf1/icons/items/inventory/scroll-magic.jpg", "documentCollection": "world.pf1-scrolls", "documentId": "zlGGZMmRjQd2UUh7", "flags": {}}, {"type": 2, "weight": 1, "range": [351, 351], "drawn": false, "text": "Scroll of Ooze Form I", "img": "systems/pf1/icons/items/inventory/scroll-magic.jpg", "documentCollection": "world.pf1-scrolls", "documentId": "zmUYioWvsHTrPhFa", "flags": {}}, {"type": 2, "weight": 1, "range": [352, 352], "drawn": false, "text": "Scroll of Absorb Toxicity", "img": "systems/pf1/icons/items/inventory/scroll-magic.jpg", "documentCollection": "world.pf1-scrolls", "documentId": "zwTK6GMa3Xtjk0wW", "flags": {}}], "formula": "1d352", "replacement": true, "displayRoll": true, "flags": {"better-rolltables": {"tags": "", "table-type": "none", "table-currency-string": "", "loot-amount-key": "", "loot-actor-name": ""}, "exportSource": {"world": "btas", "system": "dnd5e", "coreVersion": "10.290", "systemVersion": "2.0.3"}}, "_stats": {"systemId": "dnd5e", "systemVersion": "2.0.3", "coreVersion": "10.290", "createdTime": 1669241450754, "modifiedTime": 1669241521625, "lastModifiedBy": "PHZmRIBhz1kQY0PN"}}